Workbook

Sheet Planilha para aprovação
A1: Puxar do Meli | B1: Puxar do Meli | C1: Puxar do Meli | G1: Puxar o Proc p/ Tabela Padrão | H1: Comissão Real | I1: Puxar do Meli
A2: MLB | B2: SKU | C2: Redução da tarifa | D2: Tipo de anuncio | E2: Comissão Padrão | F2: % de comissão reduzida | G2: Comissão a considerar | H2: Comissão real sem limite de 4,5% | I2: Preço Final | J2: Preço segundo tabela | K2: Diferença | L2: Aprovação (com tolerancia de 5%)
A3: ='Planilha CP Meli'!B5 -> 0 | B3: ='Planilha CP Meli'!C5 -> 0 | C3: ='Planilha CP Meli'!E5 -> 0 | D3: =IFERROR(VLOOKUP(A3,'Base MLB'!A:B,2,0)," ") | E3: =IFERROR(VLOOKUP(A3,'Base MLB'!A:C,3,0)," ") | F3: =IFERROR(C3/I3," ") | G3: =IFERROR(MAX((ROUNDUP((E3-F3)*100,0)+0.5)/100,4.5%),"") | H3: =IFERROR((ROUNDUP((E3-F3)*100,0)+0.5)/100,"") | I3: ='Planilha CP Meli'!G5 -> 0 | J3: =IFERROR(INDEX('Base com preços'!$C:$O,MATCH(B3,'Base com preços'!$A:$A,0),MATCH(G3,'Base com preços'!$C$1:$O$1,0)),IFERROR(INDEX('Boa forma'!$C:$O,MATCH(A3,'Boa forma'!$A:$A,0),MATCH(G3,'Boa forma'!$C$1:$O$1,0)),"")) | K3: =IFERROR(J3-I3," ") | L3: =IFERROR(IF(K3<0,"Sim",IF(I3>=J3*0.95,"Sim","Não")),"Não") -> Não
A4: ='Planilha CP Meli'!B166 -> MLB4501497272 | B4: ='Planilha CP Meli'!C166 -> PA09773 | C4: ='Planilha CP Meli'!E166 -> 122.01 | D4: =IFERROR(VLOOKUP(A4,'Base MLB'!A:B,2,0)," ") -> Clássico | E4: =IFERROR(VLOOKUP(A4,'Base MLB'!A:C,3,0)," ") -> 0.115 | F4: =IFERROR(C4/I4," ") -> 0.079996066 | G4: =IFERROR(MAX((ROUNDUP((E4-F4)*100,0)+0.5)/100,4.5%),"") -> 0.045 | H4: =IFERROR((ROUNDUP((E4-F4)*100,0)+0.5)/100,"") -> 0.045 | I4: ='Planilha CP Meli'!G166 -> 1525.2 | J4: =IFERROR(INDEX('Base com preços'!$C:$O,MATCH(B4,'Base com preços'!$A:$A,0),MATCH(G4,'Base com preços'!$C$1:$O$1,0)),IFERROR(INDEX('Boa forma'!$C:$O,MATCH(A4,'Boa forma'!$A:$A,0),MATCH(G4,'Boa forma'!$C$1:$O$1,0)),"")) -> 1270.4531 | K4: =IFERROR(J4-I4," ") -> -254.74693 | L4: =IFERROR(IF(K4<0,"Sim",IF(I4>=J4*0.95,"Sim","Não")),"Não") -> Sim
A5: ='Planilha CP Meli'!B88 -> MLB3912235663 | B5: ='Planilha CP Meli'!C88 -> PA52309 | C5: ='Planilha CP Meli'!E88 -> 91.6 | D5: =IFERROR(VLOOKUP(A5,'Base MLB'!A:B,2,0)," ") -> Clássico | E5: =IFERROR(VLOOKUP(A5,'Base MLB'!A:C,3,0)," ") -> 0.115 | F5: =IFERROR(C5/I5," ") -> 0.066433617 | G5: =IFERROR(MAX((ROUNDUP((E5-F5)*100,0)+0.5)/100,4.5%),"") -> 0.055 | H5: =IFERROR((ROUNDUP((E5-F5)*100,0)+0.5)/100,"") -> 0.055 | I5: ='Planilha CP Meli'!G88 -> 1378.82 | J5: =IFERROR(INDEX('Base com preços'!$C:$O,MATCH(B5,'Base com preços'!$A:$A,0),MATCH(G5,'Base com preços'!$C$1:$O$1,0)),IFERROR(INDEX('Boa forma'!$C:$O,MATCH(A5,'Boa forma'!$A:$A,0),MATCH(G5,'Boa forma'!$C$1:$O$1,0)),"")) -> 1184.0385 | K5: =IFERROR(J5-I5," ") -> -194.78154 | L5: =IFERROR(IF(K5<0,"Sim",IF(I5>=J5*0.95,"Sim","Não")),"Não") -> Sim
A6: ='Planilha CP Meli'!B215 -> MLB5294222288 | B6: ='Planilha CP Meli'!C215 -> PA35622 | C6: ='Planilha CP Meli'!E215 -> 166.89 | D6: =IFERROR(VLOOKUP(A6,'Base MLB'!A:B,2,0)," ") -> Premium | E6: =IFERROR(VLOOKUP(A6,'Base MLB'!A:C,3,0)," ") -> 0.165 | F6: =IFERROR(C6/I6," ") -> 0.06910559 | G6: =IFERROR(MAX((ROUNDUP((E6-F6)*100,0)+0.5)/100,4.5%),"") -> 0.105 | H6: =IFERROR((ROUNDUP((E6-F6)*100,0)+0.5)/100,"") -> 0.105 | I6: ='Planilha CP Meli'!G215 -> 2415 | J6: =IFERROR(INDEX('Base com preços'!$C:$O,MATCH(B6,'Base com preços'!$A:$A,0),MATCH(G6,'Base com preços'!$C$1:$O$1,0)),IFERROR(INDEX('Boa forma'!$C:$O,MATCH(A6,'Boa forma'!$A:$A,0),MATCH(G6,'Boa forma'!$C$1:$O$1,0)),"")) -> 2266.6688 | K6: =IFERROR(J6-I6," ") -> -148.33117 | L6: =IFERROR(IF(K6<0,"Sim",IF(I6>=J6*0.95,"Sim","Não")),"Não") -> Sim
A7: ='Planilha CP Meli'!B205 -> MLB5189220500 | B7: ='Planilha CP Meli'!C205 -> PA94825 | C7: ='Planilha CP Meli'!E205 -> 88.83 | D7: =IFERROR(VLOOKUP(A7,'Base MLB'!A:B,2,0)," ") -> Clássico | E7: =IFERROR(VLOOKUP(A7,'Base MLB'!A:C,3,0)," ") -> 0.115 | F7: =IFERROR(C7/I7," ") -> 0.07999964 | G7: =IFERROR(MAX((ROUNDUP((E7-F7)*100,0)+0.5)/100,4.5%),"") -> 0.045 | H7: =IFERROR((ROUNDUP((E7-F7)*100,0)+0.5)/100,"") -> 0.045 | I7: ='Planilha CP Meli'!G205 -> 1110.38 | J7: =IFERROR(INDEX('Base com preços'!$C:$O,MATCH(B7,'Base com preços'!$A:$A,0),MATCH(G7,'Base com preços'!$C$1:$O$1,0)),IFERROR(INDEX('Boa forma'!$C:$O,MATCH(A7,'Boa forma'!$A:$A,0),MATCH(G7,'Boa forma'!$C$1:$O$1,0)),"")) -> 924.91597 | K7: =IFERROR(J7-I7," ") -> -185.46403 | L7: =IFERROR(IF(K7<0,"Sim",IF(I7>=J7*0.95,"Sim","Não")),"Não") -> Sim
A8: ='Planilha CP Meli'!B158 -> MLB4501394134 | B8: ='Planilha CP Meli'!C158 -> PA66410 | C8: ='Planilha CP Meli'!E158 -> 136.51 | D8: =IFERROR(VLOOKUP(A8,'Base MLB'!A:B,2,0)," ") -> Premium | E8: =IFERROR(VLOOKUP(A8,'Base MLB'!A:C,3,0)," ") -> 0.165 | F8: =IFERROR(C8/I8," ") -> 0.077001179 | G8: =IFERROR(MAX((ROUNDUP((E8-F8)*100,0)+0.5)/100,4.5%),"") -> 0.095 | H8: =IFERROR((ROUNDUP((E8-F8)*100,0)+0.5)/100,"") -> 0.095 | I8: ='Planilha CP Meli'!G158 -> 1772.83 | J8: =IFERROR(INDEX('Base com preços'!$C:$O,MATCH(B8,'Base com preços'!$A:$A,0),MATCH(G8,'Base com preços'!$C$1:$O$1,0)),IFERROR(INDEX('Boa forma'!$C:$O,MATCH(A8,'Boa forma'!$A:$A,0),MATCH(G8,'Boa forma'!$C$1:$O$1,0)),"")) -> 1719.6493 | K8: =IFERROR(J8-I8," ") -> -53.180684 | L8: =IFERROR(IF(K8<0,"Sim",IF(I8>=J8*0.95,"Sim","Não")),"Não") -> Sim
A9: ='Planilha CP Meli'!B75 -> MLB3721682233 | B9: ='Planilha CP Meli'!C75 -> PA94875 | C9: ='Planilha CP Meli'!E75 -> 119.93 | D9: =IFERROR(VLOOKUP(A9,'Base MLB'!A:B,2,0)," ") -> Premium | E9: =IFERROR(VLOOKUP(A9,'Base MLB'!A:C,3,0)," ") -> 0.165 | F9: =IFERROR(C9/I9," ") -> 0.079998132 | G9: =IFERROR(MAX((ROUNDUP((E9-F9)*100,0)+0.5)/100,4.5%),"") -> 0.095 | H9: =IFERROR((ROUNDUP((E9-F9)*100,0)+0.5)/100,"") -> 0.095 | I9: ='Planilha CP Meli'!G75 -> 1499.16 | J9: =IFERROR(INDEX('Base com preços'!$C:$O,MATCH(B9,'Base com preços'!$A:$A,0),MATCH(G9,'Base com preços'!$C$1:$O$1,0)),IFERROR(INDEX('Boa forma'!$C:$O,MATCH(A9,'Boa forma'!$A:$A,0),MATCH(G9,'Boa forma'!$C$1:$O$1,0)),"")) -> 1454.1838 | K9: =IFERROR(J9-I9," ") -> -44.976187 | L9: =IFERROR(IF(K9<0,"Sim",IF(I9>=J9*0.95,"Sim","Não")),"Não") -> Sim
A10: ='Planilha CP Meli'!B244 -> MLB5829588086 | B10: ='Planilha CP Meli'!C244 -> PA65755 | C10: ='Planilha CP Meli'!E244 -> 90.99 | D10: =IFERROR(VLOOKUP(A10,'Base MLB'!A:B,2,0)," ") -> Clássico | E10: =IFERROR(VLOOKUP(A10,'Base MLB'!A:C,3,0)," ") -> 0.115 | F10: =IFERROR(C10/I10," ") -> 0.079994725 | G10: =IFERROR(MAX((ROUNDUP((E10-F10)*100,0)+0.5)/100,4.5%),"") -> 0.045 | H10: =IFERROR((ROUNDUP((E10-F10)*100,0)+0.5)/100,"") -> 0.045 | I10: ='Planilha CP Meli'!G244 -> 1137.45 | J10: =IFERROR(INDEX('Base com preços'!$C:$O,MATCH(B10,'Base com preços'!$A:$A,0),MATCH(G10,'Base com preços'!$C$1:$O$1,0)),IFERROR(INDEX('Boa forma'!$C:$O,MATCH(A10,'Boa forma'!$A:$A,0),MATCH(G10,'Boa forma'!$C$1:$O$1,0)),"")) -> 947.47243 | K10: =IFERROR(J10-I10," ") -> -189.97757 | L10: =IFERROR(IF(K10<0,"Sim",IF(I10>=J10*0.95,"Sim","Não")),"Não") -> Sim
A11: ='Planilha CP Meli'!B74 -> MLB3671801609 | B11: ='Planilha CP Meli'!C74 -> PA85360 | C11: ='Planilha CP Meli'!E74 -> 136.82 | D11: =IFERROR(VLOOKUP(A11,'Base MLB'!A:B,2,0)," ") -> Clássico | E11: =IFERROR(VLOOKUP(A11,'Base MLB'!A:C,3,0)," ") -> 0.115 | F11: =IFERROR(C11/I11," ") -> 0.067672371 | G11: =IFERROR(MAX((ROUNDUP((E11-F11)*100,0)+0.5)/100,4.5%),"") -> 0.055 | H11: =IFERROR((ROUNDUP((E11-F11)*100,0)+0.5)/100,"") -> 0.055 | I11: ='Planilha CP Meli'!G74 -> 2021.8 | J11: =IFERROR(INDEX('Base com preços'!$C:$O,MATCH(B11,'Base com preços'!$A:$A,0),MATCH(G11,'Base com preços'!$C$1:$O$1,0)),IFERROR(INDEX('Boa forma'!$C:$O,MATCH(A11,'Boa forma'!$A:$A,0),MATCH(G11,'Boa forma'!$C$1:$O$1,0)),"")) -> 1736.1923 | K11: =IFERROR(J11-I11," ") -> -285.60775 | L11: =IFERROR(IF(K11<0,"Sim",IF(I11>=J11*0.95,"Sim","Não")),"Não") -> Sim
A12: ='Planilha CP Meli'!B123 -> MLB4240741720 | B12: ='Planilha CP Meli'!C123 -> PA66326 | C12: ='Planilha CP Meli'!E123 -> 137.2 | D12: =IFERROR(VLOOKUP(A12,'Base MLB'!A:B,2,0)," ") -> Clássico | E12: =IFERROR(VLOOKUP(A12,'Base MLB'!A:C,3,0)," ") -> 0.115 | F12: =IFERROR(C12/I12," ") -> 0.052469549 | G12: =IFERROR(MAX((ROUNDUP((E12-F12)*100,0)+0.5)/100,4.5%),"") -> 0.075 | H12: =IFERROR((ROUNDUP((E12-F12)*100,0)+0.5)/100,"") -> 0.075 | I12: ='Planilha CP Meli'!G123 -> 2614.85 | J12: =IFERROR(INDEX('Base com preços'!$C:$O,MATCH(B12,'Base com preços'!$A:$A,0),MATCH(G12,'Base com preços'!$C$1:$O$1,0)),IFERROR(INDEX('Boa forma'!$C:$O,MATCH(A12,'Boa forma'!$A:$A,0),MATCH(G12,'Boa forma'!$C$1:$O$1,0)),"")) -> 2386.5017 | K12: =IFERROR(J12-I12," ") -> -228.34827 | L12: =IFERROR(IF(K12<0,"Sim",IF(I12>=J12*0.95,"Sim","Não")),"Não") -> Sim
A13: ='Planilha CP Meli'!B77 -> MLB3732198897 | B13: ='Planilha CP Meli'!C77 -> PA66802 | C13: ='Planilha CP Meli'!E77 -> 269.79 | D13: =IFERROR(VLOOKUP(A13,'Base MLB'!A:B,2,0)," ") -> Premium | E13: =IFERROR(VLOOKUP(A13,'Base MLB'!A:C,3,0)," ") -> 0.165 | F13: =IFERROR(C13/I13," ") -> 0.064067917 | G13: =IFERROR(MAX((ROUNDUP((E13-F13)*100,0)+0.5)/100,4.5%),"") -> 0.115 | H13: =IFERROR((ROUNDUP((E13-F13)*100,0)+0.5)/100,"") -> 0.115 | I13: ='Planilha CP Meli'!G77 -> 4211 | J13: =IFERROR(INDEX('Base com preços'!$C:$O,MATCH(B13,'Base com preços'!$A:$A,0),MATCH(G13,'Base com preços'!$C$1:$O$1,0)),IFERROR(INDEX('Boa forma'!$C:$O,MATCH(A13,'Boa forma'!$A:$A,0),MATCH(G13,'Boa forma'!$C$1:$O$1,0)),"")) -> 3983.3851 | K13: =IFERROR(J13-I13," ") -> -227.61494 | L13: =IFERROR(IF(K13<0,"Sim",IF(I13>=J13*0.95,"Sim","Não")),"Não") -> Sim
A14: ='Planilha CP Meli'!B85 -> MLB3902425067 | B14: ='Planilha CP Meli'!C85 -> PA66755 | C14: ='Planilha CP Meli'!E85 -> 115.8 | D14: =IFERROR(VLOOKUP(A14,'Base MLB'!A:B,2,0)," ") -> Clássico | E14: =IFERROR(VLOOKUP(A14,'Base MLB'!A:C,3,0)," ") -> 0.115 | F14: =IFERROR(C14/I14," ") -> 0.059974208 | G14: =IFERROR(MAX((ROUNDUP((E14-F14)*100,0)+0.5)/100,4.5%),"") -> 0.065 | H14: =IFERROR((ROUNDUP((E14-F14)*100,0)+0.5)/100,"") -> 0.065 | I14: ='Planilha CP Meli'!G85 -> 1930.83 | J14: =IFERROR(INDEX('Base com preços'!$C:$O,MATCH(B14,'Base com preços'!$A:$A,0),MATCH(G14,'Base com preços'!$C$1:$O$1,0)),IFERROR(INDEX('Boa forma'!$C:$O,MATCH(A14,'Boa forma'!$A:$A,0),MATCH(G14,'Boa forma'!$C$1:$O$1,0)),"")) -> 1709.3541 | K14: =IFERROR(J14-I14," ") -> -221.4759 | L14: =IFERROR(IF(K14<0,"Sim",IF(I14>=J14*0.95,"Sim","Não")),"Não") -> Sim
A15: ='Planilha CP Meli'!B54 -> MLB3595845531 | B15: ='Planilha CP Meli'!C54 -> PA33096 | C15: ='Planilha CP Meli'!E54 -> 84.45 | D15: =IFERROR(VLOOKUP(A15,'Base MLB'!A:B,2,0)," ") -> Clássico | E15: =IFERROR(VLOOKUP(A15,'Base MLB'!A:C,3,0)," ") -> 0.115 | F15: =IFERROR(C15/I15," ") -> 0.057593551 | G15: =IFERROR(MAX((ROUNDUP((E15-F15)*100,0)+0.5)/100,4.5%),"") -> 0.065 | H15: =IFERROR((ROUNDUP((E15-F15)*100,0)+0.5)/100,"") -> 0.065 | I15: ='Planilha CP Meli'!G54 -> 1466.31 | J15: =IFERROR(INDEX('Base com preços'!$C:$O,MATCH(B15,'Base com preços'!$A:$A,0),MATCH(G15,'Base com preços'!$C$1:$O$1,0)),IFERROR(INDEX('Boa forma'!$C:$O,MATCH(A15,'Boa forma'!$A:$A,0),MATCH(G15,'Boa forma'!$C$1:$O$1,0)),"")) -> 1298.1165 | K15: =IFERROR(J15-I15," ") -> -168.19349 | L15: =IFERROR(IF(K15<0,"Sim",IF(I15>=J15*0.95,"Sim","Não")),"Não") -> Sim
A16: ='Planilha CP Meli'!B79 -> MLB3871324883 | B16: ='Planilha CP Meli'!C79 -> PA66799 | C16: ='Planilha CP Meli'!E79 -> 310.58 | D16: =IFERROR(VLOOKUP(A16,'Base MLB'!A:B,2,0)," ") -> Premium | E16: =IFERROR(VLOOKUP(A16,'Base MLB'!A:C,3,0)," ") -> 0.165 | F16: =IFERROR(C16/I16," ") -> 0.079997939 | G16: =IFERROR(MAX((ROUNDUP((E16-F16)*100,0)+0.5)/100,4.5%),"") -> 0.095 | H16: =IFERROR((ROUNDUP((E16-F16)*100,0)+0.5)/100,"") -> 0.095 | I16: ='Planilha CP Meli'!G79 -> 3882.35 | J16: =IFERROR(INDEX('Base com preços'!$C:$O,MATCH(B16,'Base com preços'!$A:$A,0),MATCH(G16,'Base com preços'!$C$1:$O$1,0)),IFERROR(INDEX('Boa forma'!$C:$O,MATCH(A16,'Boa forma'!$A:$A,0),MATCH(G16,'Boa forma'!$C$1:$O$1,0)),"")) -> 3765.8778 | K16: =IFERROR(J16-I16," ") -> -116.47216 | L16: =IFERROR(IF(K16<0,"Sim",IF(I16>=J16*0.95,"Sim","Não")),"Não") -> Sim
A17: ='Planilha CP Meli'!B195 -> MLB5184852518 | B17: ='Planilha CP Meli'!C195 -> PA52004 | C17: ='Planilha CP Meli'!E195 -> 74.25 | D17: =IFERROR(VLOOKUP(A17,'Base MLB'!A:B,2,0)," ") -> Clássico | E17: =IFERROR(VLOOKUP(A17,'Base MLB'!A:C,3,0)," ") -> 0.115 | F17: =IFERROR(C17/I17," ") -> 0.061700696 | G17: =IFERROR(MAX((ROUNDUP((E17-F17)*100,0)+0.5)/100,4.5%),"") -> 0.065 | H17: =IFERROR((ROUNDUP((E17-F17)*100,0)+0.5)/100,"") -> 0.065 | I17: ='Planilha CP Meli'!G195 -> 1203.39 | J17: =IFERROR(INDEX('Base com preços'!$C:$O,MATCH(B17,'Base com preços'!$A:$A,0),MATCH(G17,'Base com preços'!$C$1:$O$1,0)),IFERROR(INDEX('Boa forma'!$C:$O,MATCH(A17,'Boa forma'!$A:$A,0),MATCH(G17,'Boa forma'!$C$1:$O$1,0)),"")) -> 1065.3546 | K17: =IFERROR(J17-I17," ") -> -138.03536 | L17: =IFERROR(IF(K17<0,"Sim",IF(I17>=J17*0.95,"Sim","Não")),"Não") -> Sim
A18: ='Planilha CP Meli'!B21 -> MLB3509789731 | B18: ='Planilha CP Meli'!C21 -> PA66798 | C18: ='Planilha CP Meli'!E21 -> 183.69 | D18: =IFERROR(VLOOKUP(A18,'Base MLB'!A:B,2,0)," ") -> Clássico | E18: =IFERROR(VLOOKUP(A18,'Base MLB'!A:C,3,0)," ") -> 0.115 | F18: =IFERROR(C18/I18," ") -> 0.057367808 | G18: =IFERROR(MAX((ROUNDUP((E18-F18)*100,0)+0.5)/100,4.5%),"") -> 0.065 | H18: =IFERROR((ROUNDUP((E18-F18)*100,0)+0.5)/100,"") -> 0.065 | I18: ='Planilha CP Meli'!G21 -> 3201.97 | J18: =IFERROR(INDEX('Base com preços'!$C:$O,MATCH(B18,'Base com preços'!$A:$A,0),MATCH(G18,'Base com preços'!$C$1:$O$1,0)),IFERROR(INDEX('Boa forma'!$C:$O,MATCH(A18,'Boa forma'!$A:$A,0),MATCH(G18,'Boa forma'!$C$1:$O$1,0)),"")) -> 2834.6849 | K18: =IFERROR(J18-I18," ") -> -367.28514 | L18: =IFERROR(IF(K18<0,"Sim",IF(I18>=J18*0.95,"Sim","Não")),"Não") -> Sim
A19: ='Planilha CP Meli'!B22 -> MLB3521713879 | B19: ='Planilha CP Meli'!C22 -> PA66792 | C19: ='Planilha CP Meli'!E22 -> 134.43 | D19: =IFERROR(VLOOKUP(A19,'Base MLB'!A:B,2,0)," ") -> Premium | E19: =IFERROR(VLOOKUP(A19,'Base MLB'!A:C,3,0)," ") -> 0.165 | F19: =IFERROR(C19/I19," ") -> 0.067667016 | G19: =IFERROR(MAX((ROUNDUP((E19-F19)*100,0)+0.5)/100,4.5%),"") -> 0.105 | H19: =IFERROR((ROUNDUP((E19-F19)*100,0)+0.5)/100,"") -> 0.105 | I19: ='Planilha CP Meli'!G22 -> 1986.64 | J19: =IFERROR(INDEX('Base com preços'!$C:$O,MATCH(B19,'Base com preços'!$A:$A,0),MATCH(G19,'Base com preços'!$C$1:$O$1,0)),IFERROR(INDEX('Boa forma'!$C:$O,MATCH(A19,'Boa forma'!$A:$A,0),MATCH(G19,'Boa forma'!$C$1:$O$1,0)),"")) -> 1986.6375 | K19: =IFERROR(J19-I19," ") -> -0.0024995938 | L19: =IFERROR(IF(K19<0,"Sim",IF(I19>=J19*0.95,"Sim","Não")),"Não") -> Sim
A20: ='Planilha CP Meli'!B73 -> MLB3671718537 | B20: ='Planilha CP Meli'!C73 -> PA85350 | C20: ='Planilha CP Meli'!E73 -> 184 | D20: =IFERROR(VLOOKUP(A20,'Base MLB'!A:B,2,0)," ") -> Premium | E20: =IFERROR(VLOOKUP(A20,'Base MLB'!A:C,3,0)," ") -> 0.165 | F20: =IFERROR(C20/I20," ") -> 0.08 | G20: =IFERROR(MAX((ROUNDUP((E20-F20)*100,0)+0.5)/100,4.5%),"") -> 0.095 | H20: =IFERROR((ROUNDUP((E20-F20)*100,0)+0.5)/100,"") -> 0.095 | I20: ='Planilha CP Meli'!G73 -> 2300 | J20: =IFERROR(INDEX('Base com preços'!$C:$O,MATCH(B20,'Base com preços'!$A:$A,0),MATCH(G20,'Base com preços'!$C$1:$O$1,0)),IFERROR(INDEX('Boa forma'!$C:$O,MATCH(A20,'Boa forma'!$A:$A,0),MATCH(G20,'Boa forma'!$C$1:$O$1,0)),"")) -> 2093.5807 | K20: =IFERROR(J20-I20," ") -> -206.41929 | L20: =IFERROR(IF(K20<0,"Sim",IF(I20>=J20*0.95,"Sim","Não")),"Não") -> Sim
A21: ='Planilha CP Meli'!B72 -> MLB3647966463 | B21: ='Planilha CP Meli'!C72 -> PA66797 | C21: ='Planilha CP Meli'!E72 -> 218.49 | D21: =IFERROR(VLOOKUP(A21,'Base MLB'!A:B,2,0)," ") -> Premium | E21: =IFERROR(VLOOKUP(A21,'Base MLB'!A:C,3,0)," ") -> 0.165 | F21: =IFERROR(C21/I21," ") -> 0.074876628 | G21: =IFERROR(MAX((ROUNDUP((E21-F21)*100,0)+0.5)/100,4.5%),"") -> 0.105 | H21: =IFERROR((ROUNDUP((E21-F21)*100,0)+0.5)/100,"") -> 0.105 | I21: ='Planilha CP Meli'!G72 -> 2918 | J21: =IFERROR(INDEX('Base com preços'!$C:$O,MATCH(B21,'Base com preços'!$A:$A,0),MATCH(G21,'Base com preços'!$C$1:$O$1,0)),IFERROR(INDEX('Boa forma'!$C:$O,MATCH(A21,'Boa forma'!$A:$A,0),MATCH(G21,'Boa forma'!$C$1:$O$1,0)),"")) -> 2650.6962 | K21: =IFERROR(J21-I21," ") -> -267.30376 | L21: =IFERROR(IF(K21<0,"Sim",IF(I21>=J21*0.95,"Sim","Não")),"Não") -> Sim
A22: ='Planilha CP Meli'!B61 -> MLB3595908405 | B22: ='Planilha CP Meli'!C61 -> PA62218 | C22: ='Planilha CP Meli'!E61 -> 74.22 | D22: =IFERROR(VLOOKUP(A22,'Base MLB'!A:B,2,0)," ") -> Clássico | E22: =IFERROR(VLOOKUP(A22,'Base MLB'!A:C,3,0)," ") -> 0.115 | F22: =IFERROR(C22/I22," ") -> 0.064670721 | G22: =IFERROR(MAX((ROUNDUP((E22-F22)*100,0)+0.5)/100,4.5%),"") -> 0.065 | H22: =IFERROR((ROUNDUP((E22-F22)*100,0)+0.5)/100,"") -> 0.065 | I22: ='Planilha CP Meli'!G61 -> 1147.66 | J22: =IFERROR(INDEX('Base com preços'!$C:$O,MATCH(B22,'Base com preços'!$A:$A,0),MATCH(G22,'Base com preços'!$C$1:$O$1,0)),IFERROR(INDEX('Boa forma'!$C:$O,MATCH(A22,'Boa forma'!$A:$A,0),MATCH(G22,'Boa forma'!$C$1:$O$1,0)),"")) -> 1016.0181 | K22: =IFERROR(J22-I22," ") -> -131.64185 | L22: =IFERROR(IF(K22<0,"Sim",IF(I22>=J22*0.95,"Sim","Não")),"Não") -> Sim
A23: ='Planilha CP Meli'!B20 -> MLB3507036477 | B23: ='Planilha CP Meli'!C20 -> PA66798 | C23: ='Planilha CP Meli'!E20 -> 232.9 | D23: =IFERROR(VLOOKUP(A23,'Base MLB'!A:B,2,0)," ") -> Premium | E23: =IFERROR(VLOOKUP(A23,'Base MLB'!A:C,3,0)," ") -> 0.165 | F23: =IFERROR(C23/I23," ") -> 0.070108368 | G23: =IFERROR(MAX((ROUNDUP((E23-F23)*100,0)+0.5)/100,4.5%),"") -> 0.105 | H23: =IFERROR((ROUNDUP((E23-F23)*100,0)+0.5)/100,"") -> 0.105 | I23: ='Planilha CP Meli'!G20 -> 3322 | J23: =IFERROR(INDEX('Base com preços'!$C:$O,MATCH(B23,'Base com preços'!$A:$A,0),MATCH(G23,'Base com preços'!$C$1:$O$1,0)),IFERROR(INDEX('Boa forma'!$C:$O,MATCH(A23,'Boa forma'!$A:$A,0),MATCH(G23,'Boa forma'!$C$1:$O$1,0)),"")) -> 3201.9743 | K23: =IFERROR(J23-I23," ") -> -120.02566 | L23: =IFERROR(IF(K23<0,"Sim",IF(I23>=J23*0.95,"Sim","Não")),"Não") -> Sim
A24: ='Planilha CP Meli'!B82 -> MLB3902407539 | B24: ='Planilha CP Meli'!C82 -> PA94856 | C24: ='Planilha CP Meli'!E82 -> 136.4 | D24: =IFERROR(VLOOKUP(A24,'Base MLB'!A:B,2,0)," ") -> Premium | E24: =IFERROR(VLOOKUP(A24,'Base MLB'!A:C,3,0)," ") -> 0.165 | F24: =IFERROR(C24/I24," ") -> 0.079999062 | G24: =IFERROR(MAX((ROUNDUP((E24-F24)*100,0)+0.5)/100,4.5%),"") -> 0.095 | H24: =IFERROR((ROUNDUP((E24-F24)*100,0)+0.5)/100,"") -> 0.095 | I24: ='Planilha CP Meli'!G82 -> 1705.02 | J24: =IFERROR(INDEX('Base com preços'!$C:$O,MATCH(B24,'Base com preços'!$A:$A,0),MATCH(G24,'Base com preços'!$C$1:$O$1,0)),IFERROR(INDEX('Boa forma'!$C:$O,MATCH(A24,'Boa forma'!$A:$A,0),MATCH(G24,'Boa forma'!$C$1:$O$1,0)),"")) -> 1653.865 | K24: =IFERROR(J24-I24," ") -> -51.154975 | L24: =IFERROR(IF(K24<0,"Sim",IF(I24>=J24*0.95,"Sim","Não")),"Não") -> Sim
A25: ='Planilha CP Meli'!B86 -> MLB3902435363 | B25: ='Planilha CP Meli'!C86 -> PA52109 | C25: ='Planilha CP Meli'!E86 -> 141.33 | D25: =IFERROR(VLOOKUP(A25,'Base MLB'!A:B,2,0)," ") -> Clássico | E25: =IFERROR(VLOOKUP(A25,'Base MLB'!A:C,3,0)," ") -> 0.115 | F25: =IFERROR(C25/I25," ") -> 0.051968539 | G25: =IFERROR(MAX((ROUNDUP((E25-F25)*100,0)+0.5)/100,4.5%),"") -> 0.075 | H25: =IFERROR((ROUNDUP((E25-F25)*100,0)+0.5)/100,"") -> 0.075 | I25: ='Planilha CP Meli'!G86 -> 2719.53 | J25: =IFERROR(INDEX('Base com preços'!$C:$O,MATCH(B25,'Base com preços'!$A:$A,0),MATCH(G25,'Base com preços'!$C$1:$O$1,0)),IFERROR(INDEX('Boa forma'!$C:$O,MATCH(A25,'Boa forma'!$A:$A,0),MATCH(G25,'Boa forma'!$C$1:$O$1,0)),"")) -> 2482.0505 | K25: =IFERROR(J25-I25," ") -> -237.47952 | L25: =IFERROR(IF(K25<0,"Sim",IF(I25>=J25*0.95,"Sim","Não")),"Não") -> Sim
A26: ='Planilha CP Meli'!B87 -> MLB3912222983 | B26: ='Planilha CP Meli'!C87 -> PA52131 | C26: ='Planilha CP Meli'!E87 -> 40.19 | D26: =IFERROR(VLOOKUP(A26,'Base MLB'!A:B,2,0)," ") -> Clássico | E26: =IFERROR(VLOOKUP(A26,'Base MLB'!A:C,3,0)," ") -> 0.115 | F26: =IFERROR(C26/I26," ") -> 0.051005127 | G26: =IFERROR(MAX((ROUNDUP((E26-F26)*100,0)+0.5)/100,4.5%),"") -> 0.075 | H26: =IFERROR((ROUNDUP((E26-F26)*100,0)+0.5)/100,"") -> 0.075 | I26: ='Planilha CP Meli'!G87 -> 787.96 | J26: =IFERROR(INDEX('Base com preços'!$C:$O,MATCH(B26,'Base com preços'!$A:$A,0),MATCH(G26,'Base com preços'!$C$1:$O$1,0)),IFERROR(INDEX('Boa forma'!$C:$O,MATCH(A26,'Boa forma'!$A:$A,0),MATCH(G26,'Boa forma'!$C$1:$O$1,0)),"")) -> 719.15619 | K26: =IFERROR(J26-I26," ") -> -68.803813 | L26: =IFERROR(IF(K26<0,"Sim",IF(I26>=J26*0.95,"Sim","Não")),"Não") -> Sim
A27: ='Planilha CP Meli'!B9 -> MLB3474507063 | B27: ='Planilha CP Meli'!C9 -> PA66716 | C27: ='Planilha CP Meli'!E9 -> 197.84 | D27: =IFERROR(VLOOKUP(A27,'Base MLB'!A:B,2,0)," ") -> Premium | E27: =IFERROR(VLOOKUP(A27,'Base MLB'!A:C,3,0)," ") -> 0.165 | F27: =IFERROR(C27/I27," ") -> 0.08 | G27: =IFERROR(MAX((ROUNDUP((E27-F27)*100,0)+0.5)/100,4.5%),"") -> 0.095 | H27: =IFERROR((ROUNDUP((E27-F27)*100,0)+0.5)/100,"") -> 0.095 | I27: ='Planilha CP Meli'!G9 -> 2473 | J27: =IFERROR(INDEX('Base com preços'!$C:$O,MATCH(B27,'Base com preços'!$A:$A,0),MATCH(G27,'Base com preços'!$C$1:$O$1,0)),IFERROR(INDEX('Boa forma'!$C:$O,MATCH(A27,'Boa forma'!$A:$A,0),MATCH(G27,'Boa forma'!$C$1:$O$1,0)),"")) -> 2655.496 | K27: =IFERROR(J27-I27," ") -> 182.49601 | L27: =IFERROR(IF(K27<0,"Sim",IF(I27>=J27*0.95,"Sim","Não")),"Não") -> Não
A28: ='Planilha CP Meli'!B64 -> MLB3595927625 | B28: ='Planilha CP Meli'!C64 -> PA56269 | C28: ='Planilha CP Meli'!E64 -> 172.87 | D28: =IFERROR(VLOOKUP(A28,'Base MLB'!A:B,2,0)," ") -> Premium | E28: =IFERROR(VLOOKUP(A28,'Base MLB'!A:C,3,0)," ") -> 0.165 | F28: =IFERROR(C28/I28," ") -> 0.079996483 | G28: =IFERROR(MAX((ROUNDUP((E28-F28)*100,0)+0.5)/100,4.5%),"") -> 0.095 | H28: =IFERROR((ROUNDUP((E28-F28)*100,0)+0.5)/100,"") -> 0.095 | I28: ='Planilha CP Meli'!G64 -> 2160.97 | J28: =IFERROR(INDEX('Base com preços'!$C:$O,MATCH(B28,'Base com preços'!$A:$A,0),MATCH(G28,'Base com preços'!$C$1:$O$1,0)),IFERROR(INDEX('Boa forma'!$C:$O,MATCH(A28,'Boa forma'!$A:$A,0),MATCH(G28,'Boa forma'!$C$1:$O$1,0)),"")) -> 2096.1384 | K28: =IFERROR(J28-I28," ") -> -64.831594 | L28: =IFERROR(IF(K28<0,"Sim",IF(I28>=J28*0.95,"Sim","Não")),"Não") -> Sim
A29: ='Planilha CP Meli'!B55 -> MLB3595858305 | B29: ='Planilha CP Meli'!C55 -> PA62215 | C29: ='Planilha CP Meli'!E55 -> 45.64 | D29: =IFERROR(VLOOKUP(A29,'Base MLB'!A:B,2,0)," ") -> Clássico | E29: =IFERROR(VLOOKUP(A29,'Base MLB'!A:C,3,0)," ") -> 0.115 | F29: =IFERROR(C29/I29," ") -> 0.07 | G29: =IFERROR(MAX((ROUNDUP((E29-F29)*100,0)+0.5)/100,4.5%),"") -> 0.055 | H29: =IFERROR((ROUNDUP((E29-F29)*100,0)+0.5)/100,"") -> 0.055 | I29: ='Planilha CP Meli'!G55 -> 652 | J29: =IFERROR(INDEX('Base com preços'!$C:$O,MATCH(B29,'Base com preços'!$A:$A,0),MATCH(G29,'Base com preços'!$C$1:$O$1,0)),IFERROR(INDEX('Boa forma'!$C:$O,MATCH(A29,'Boa forma'!$A:$A,0),MATCH(G29,'Boa forma'!$C$1:$O$1,0)),"")) -> 646.93315 | K29: =IFERROR(J29-I29," ") -> -5.0668532 | L29: =IFERROR(IF(K29<0,"Sim",IF(I29>=J29*0.95,"Sim","Não")),"Não") -> Sim
A30: ='Planilha CP Meli'!B212 -> MLB5273989912 | B30: ='Planilha CP Meli'!C212 -> PA66715 | C30: ='Planilha CP Meli'!E212 -> 143.04 | D30: =IFERROR(VLOOKUP(A30,'Base MLB'!A:B,2,0)," ") -> Clássico | E30: =IFERROR(VLOOKUP(A30,'Base MLB'!A:C,3,0)," ") -> 0.115 | F30: =IFERROR(C30/I30," ") -> 0.08 | G30: =IFERROR(MAX((ROUNDUP((E30-F30)*100,0)+0.5)/100,4.5%),"") -> 0.045 | H30: =IFERROR((ROUNDUP((E30-F30)*100,0)+0.5)/100,"") -> 0.045 | I30: ='Planilha CP Meli'!G212 -> 1788 | J30: =IFERROR(INDEX('Base com preços'!$C:$O,MATCH(B30,'Base com preços'!$A:$A,0),MATCH(G30,'Base com preços'!$C$1:$O$1,0)),IFERROR(INDEX('Boa forma'!$C:$O,MATCH(A30,'Boa forma'!$A:$A,0),MATCH(G30,'Boa forma'!$C$1:$O$1,0)),"")) -> 1931.0265 | K30: =IFERROR(J30-I30," ") -> 143.02649 | L30: =IFERROR(IF(K30<0,"Sim",IF(I30>=J30*0.95,"Sim","Não")),"Não") -> Não
A31: ='Planilha CP Meli'!B31 -> MLB3550443351 | B31: ='Planilha CP Meli'!C31 -> PA66406 | C31: ='Planilha CP Meli'!E31 -> 92.16 | D31: =IFERROR(VLOOKUP(A31,'Base MLB'!A:B,2,0)," ") -> Premium | E31: =IFERROR(VLOOKUP(A31,'Base MLB'!A:C,3,0)," ") -> 0.165 | F31: =IFERROR(C31/I31," ") -> 0.08 | G31: =IFERROR(MAX((ROUNDUP((E31-F31)*100,0)+0.5)/100,4.5%),"") -> 0.095 | H31: =IFERROR((ROUNDUP((E31-F31)*100,0)+0.5)/100,"") -> 0.095 | I31: ='Planilha CP Meli'!G31 -> 1152 | J31: =IFERROR(INDEX('Base com preços'!$C:$O,MATCH(B31,'Base com preços'!$A:$A,0),MATCH(G31,'Base com preços'!$C$1:$O$1,0)),IFERROR(INDEX('Boa forma'!$C:$O,MATCH(A31,'Boa forma'!$A:$A,0),MATCH(G31,'Boa forma'!$C$1:$O$1,0)),"")) -> 1120.6752 | K31: =IFERROR(J31-I31," ") -> -31.324818 | L31: =IFERROR(IF(K31<0,"Sim",IF(I31>=J31*0.95,"Sim","Não")),"Não") -> Sim
A32: ='Planilha CP Meli'!B11 -> MLB3474545857 | B32: ='Planilha CP Meli'!C11 -> PA66724 | C32: ='Planilha CP Meli'!E11 -> 162.02 | D32: =IFERROR(VLOOKUP(A32,'Base MLB'!A:B,2,0)," ") -> Premium | E32: =IFERROR(VLOOKUP(A32,'Base MLB'!A:C,3,0)," ") -> 0.165 | F32: =IFERROR(C32/I32," ") -> 0.07999526 | G32: =IFERROR(MAX((ROUNDUP((E32-F32)*100,0)+0.5)/100,4.5%),"") -> 0.095 | H32: =IFERROR((ROUNDUP((E32-F32)*100,0)+0.5)/100,"") -> 0.095 | I32: ='Planilha CP Meli'!G11 -> 2025.37 | J32: =IFERROR(INDEX('Base com preços'!$C:$O,MATCH(B32,'Base com preços'!$A:$A,0),MATCH(G32,'Base com preços'!$C$1:$O$1,0)),IFERROR(INDEX('Boa forma'!$C:$O,MATCH(A32,'Boa forma'!$A:$A,0),MATCH(G32,'Boa forma'!$C$1:$O$1,0)),"")) -> 1964.6046 | K32: =IFERROR(J32-I32," ") -> -60.765424 | L32: =IFERROR(IF(K32<0,"Sim",IF(I32>=J32*0.95,"Sim","Não")),"Não") -> Sim
A33: ='Planilha CP Meli'!B10 -> MLB3474545447 | B33: ='Planilha CP Meli'!C10 -> PA85357 | C33: ='Planilha CP Meli'!E10 -> 107.34 | D33: =IFERROR(VLOOKUP(A33,'Base MLB'!A:B,2,0)," ") -> Premium | E33: =IFERROR(VLOOKUP(A33,'Base MLB'!A:C,3,0)," ") -> 0.165 | F33: =IFERROR(C33/I33," ") -> 0.079997019 | G33: =IFERROR(MAX((ROUNDUP((E33-F33)*100,0)+0.5)/100,4.5%),"") -> 0.095 | H33: =IFERROR((ROUNDUP((E33-F33)*100,0)+0.5)/100,"") -> 0.095 | I33: ='Planilha CP Meli'!G10 -> 1341.8 | J33: =IFERROR(INDEX('Base com preços'!$C:$O,MATCH(B33,'Base com preços'!$A:$A,0),MATCH(G33,'Base com preços'!$C$1:$O$1,0)),IFERROR(INDEX('Boa forma'!$C:$O,MATCH(A33,'Boa forma'!$A:$A,0),MATCH(G33,'Boa forma'!$C$1:$O$1,0)),"")) -> 1301.542 | K33: =IFERROR(J33-I33," ") -> -40.257982 | L33: =IFERROR(IF(K33<0,"Sim",IF(I33>=J33*0.95,"Sim","Não")),"Não") -> Sim
A34: ='Planilha CP Meli'!B38 -> MLB3556422353 | B34: ='Planilha CP Meli'!C38 -> PA56268 | C34: ='Planilha CP Meli'!E38 -> 131.36 | D34: =IFERROR(VLOOKUP(A34,'Base MLB'!A:B,2,0)," ") -> Premium | E34: =IFERROR(VLOOKUP(A34,'Base MLB'!A:C,3,0)," ") -> 0.165 | F34: =IFERROR(C34/I34," ") -> 0.08 | G34: =IFERROR(MAX((ROUNDUP((E34-F34)*100,0)+0.5)/100,4.5%),"") -> 0.095 | H34: =IFERROR((ROUNDUP((E34-F34)*100,0)+0.5)/100,"") -> 0.095 | I34: ='Planilha CP Meli'!G38 -> 1642 | J34: =IFERROR(INDEX('Base com preços'!$C:$O,MATCH(B34,'Base com preços'!$A:$A,0),MATCH(G34,'Base com preços'!$C$1:$O$1,0)),IFERROR(INDEX('Boa forma'!$C:$O,MATCH(A34,'Boa forma'!$A:$A,0),MATCH(G34,'Boa forma'!$C$1:$O$1,0)),"")) -> 1752.6075 | K34: =IFERROR(J34-I34," ") -> 110.60749 | L34: =IFERROR(IF(K34<0,"Sim",IF(I34>=J34*0.95,"Sim","Não")),"Não") -> Não
A35: ='Planilha CP Meli'!B36 -> MLB3556253923 | B35: ='Planilha CP Meli'!C36 -> PA66420 | C35: ='Planilha CP Meli'!E36 -> 125.1 | D35: =IFERROR(VLOOKUP(A35,'Base MLB'!A:B,2,0)," ") -> Premium | E35: =IFERROR(VLOOKUP(A35,'Base MLB'!A:C,3,0)," ") -> 0.165 | F35: =IFERROR(C35/I35," ") -> 0.079994884 | G35: =IFERROR(MAX((ROUNDUP((E35-F35)*100,0)+0.5)/100,4.5%),"") -> 0.095 | H35: =IFERROR((ROUNDUP((E35-F35)*100,0)+0.5)/100,"") -> 0.095 | I35: ='Planilha CP Meli'!G36 -> 1563.85 | J35: =IFERROR(INDEX('Base com preços'!$C:$O,MATCH(B35,'Base com preços'!$A:$A,0),MATCH(G35,'Base com preços'!$C$1:$O$1,0)),IFERROR(INDEX('Boa forma'!$C:$O,MATCH(A35,'Boa forma'!$A:$A,0),MATCH(G35,'Boa forma'!$C$1:$O$1,0)),"")) -> 1516.9308 | K35: =IFERROR(J35-I35," ") -> -46.919164 | L35: =IFERROR(IF(K35<0,"Sim",IF(I35>=J35*0.95,"Sim","Não")),"Não") -> Sim
A36: ='Planilha CP Meli'!B16 -> MLB3482170647 | B36: ='Planilha CP Meli'!C16 -> PA66724 | C36: ='Planilha CP Meli'!E16 -> 95.46 | D36: =IFERROR(VLOOKUP(A36,'Base MLB'!A:B,2,0)," ") -> Clássico | E36: =IFERROR(VLOOKUP(A36,'Base MLB'!A:C,3,0)," ") -> 0.115 | F36: =IFERROR(C36/I36," ") -> 0.047132362 | G36: =IFERROR(MAX((ROUNDUP((E36-F36)*100,0)+0.5)/100,4.5%),"") -> 0.075 | H36: =IFERROR((ROUNDUP((E36-F36)*100,0)+0.5)/100,"") -> 0.075 | I36: ='Planilha CP Meli'!G16 -> 2025.36 | J36: =IFERROR(INDEX('Base com preços'!$C:$O,MATCH(B36,'Base com preços'!$A:$A,0),MATCH(G36,'Base com preços'!$C$1:$O$1,0)),IFERROR(INDEX('Boa forma'!$C:$O,MATCH(A36,'Boa forma'!$A:$A,0),MATCH(G36,'Boa forma'!$C$1:$O$1,0)),"")) -> 1848.4964 | K36: =IFERROR(J36-I36," ") -> -176.86355 | L36: =IFERROR(IF(K36<0,"Sim",IF(I36>=J36*0.95,"Sim","Não")),"Não") -> Sim
A37: ='Planilha CP Meli'!B114 -> MLB4144905284 | B37: ='Planilha CP Meli'!C114 -> PA66795 | C37: ='Planilha CP Meli'!E114 -> 225.72 | D37: =IFERROR(VLOOKUP(A37,'Base MLB'!A:B,2,0)," ") -> Clássico | E37: =IFERROR(VLOOKUP(A37,'Base MLB'!A:C,3,0)," ") -> 0.115 | F37: =IFERROR(C37/I37," ") -> 0.052605943 | G37: =IFERROR(MAX((ROUNDUP((E37-F37)*100,0)+0.5)/100,4.5%),"") -> 0.075 | H37: =IFERROR((ROUNDUP((E37-F37)*100,0)+0.5)/100,"") -> 0.075 | I37: ='Planilha CP Meli'!G114 -> 4290.77 | J37: =IFERROR(INDEX('Base com preços'!$C:$O,MATCH(B37,'Base com preços'!$A:$A,0),MATCH(G37,'Base com preços'!$C$1:$O$1,0)),IFERROR(INDEX('Boa forma'!$C:$O,MATCH(A37,'Boa forma'!$A:$A,0),MATCH(G37,'Boa forma'!$C$1:$O$1,0)),"")) -> 3916.0664 | K37: =IFERROR(J37-I37," ") -> -374.7036 | L37: =IFERROR(IF(K37<0,"Sim",IF(I37>=J37*0.95,"Sim","Não")),"Não") -> Sim
A38: ='Planilha CP Meli'!B40 -> MLB3569840133 | B38: ='Planilha CP Meli'!C40 -> PA51667 | C38: ='Planilha CP Meli'!E40 -> 33.18 | D38: =IFERROR(VLOOKUP(A38,'Base MLB'!A:B,2,0)," ") -> Premium | E38: =IFERROR(VLOOKUP(A38,'Base MLB'!A:C,3,0)," ") -> 0.165 | F38: =IFERROR(C38/I38," ") -> 0.07 | G38: =IFERROR(MAX((ROUNDUP((E38-F38)*100,0)+0.5)/100,4.5%),"") -> 0.105 | H38: =IFERROR((ROUNDUP((E38-F38)*100,0)+0.5)/100,"") -> 0.105 | I38: ='Planilha CP Meli'!G40 -> 474 | J38: =IFERROR(INDEX('Base com preços'!$C:$O,MATCH(B38,'Base com preços'!$A:$A,0),MATCH(G38,'Base com preços'!$C$1:$O$1,0)),IFERROR(INDEX('Boa forma'!$C:$O,MATCH(A38,'Boa forma'!$A:$A,0),MATCH(G38,'Boa forma'!$C$1:$O$1,0)),"")) -> 584.84001 | K38: =IFERROR(J38-I38," ") -> 110.84001 | L38: =IFERROR(IF(K38<0,"Sim",IF(I38>=J38*0.95,"Sim","Não")),"Não") -> Não
A39: ='Planilha CP Meli'!B202 -> MLB5186926186 | B39: ='Planilha CP Meli'!C202 -> PA94860 | C39: ='Planilha CP Meli'!E202 -> 106.03 | D39: =IFERROR(VLOOKUP(A39,'Base MLB'!A:B,2,0)," ") -> Clássico | E39: =IFERROR(VLOOKUP(A39,'Base MLB'!A:C,3,0)," ") -> 0.115 | F39: =IFERROR(C39/I39," ") -> 0.079996077 | G39: =IFERROR(MAX((ROUNDUP((E39-F39)*100,0)+0.5)/100,4.5%),"") -> 0.045 | H39: =IFERROR((ROUNDUP((E39-F39)*100,0)+0.5)/100,"") -> 0.045 | I39: ='Planilha CP Meli'!G202 -> 1325.44 | J39: =IFERROR(INDEX('Base com preços'!$C:$O,MATCH(B39,'Base com preços'!$A:$A,0),MATCH(G39,'Base com preços'!$C$1:$O$1,0)),IFERROR(INDEX('Boa forma'!$C:$O,MATCH(A39,'Boa forma'!$A:$A,0),MATCH(G39,'Boa forma'!$C$1:$O$1,0)),"")) -> 1104.0525 | K39: =IFERROR(J39-I39," ") -> -221.38751 | L39: =IFERROR(IF(K39<0,"Sim",IF(I39>=J39*0.95,"Sim","Não")),"Não") -> Sim
A40: ='Planilha CP Meli'!B30 -> MLB3548950907 | B40: ='Planilha CP Meli'!C30 -> PA69851 | C40: ='Planilha CP Meli'!E30 -> 191.76 | D40: =IFERROR(VLOOKUP(A40,'Base MLB'!A:B,2,0)," ") -> Premium | E40: =IFERROR(VLOOKUP(A40,'Base MLB'!A:C,3,0)," ") -> 0.165 | F40: =IFERROR(C40/I40," ") -> 0.08 | G40: =IFERROR(MAX((ROUNDUP((E40-F40)*100,0)+0.5)/100,4.5%),"") -> 0.095 | H40: =IFERROR((ROUNDUP((E40-F40)*100,0)+0.5)/100,"") -> 0.095 | I40: ='Planilha CP Meli'!G30 -> 2397 | J40: =IFERROR(INDEX('Base com preços'!$C:$O,MATCH(B40,'Base com preços'!$A:$A,0),MATCH(G40,'Base com preços'!$C$1:$O$1,0)),IFERROR(INDEX('Boa forma'!$C:$O,MATCH(A40,'Boa forma'!$A:$A,0),MATCH(G40,'Boa forma'!$C$1:$O$1,0)),"")) -> 2181.9534 | K40: =IFERROR(J40-I40," ") -> -215.04663 | L40: =IFERROR(IF(K40<0,"Sim",IF(I40>=J40*0.95,"Sim","Não")),"Não") -> Sim
A41: ='Planilha CP Meli'!B6 -> MLB3473649173 | B41: ='Planilha CP Meli'!C6 -> PA85366 | C41: ='Planilha CP Meli'!E6 -> 100.98 | D41: =IFERROR(VLOOKUP(A41,'Base MLB'!A:B,2,0)," ") -> Clássico | E41: =IFERROR(VLOOKUP(A41,'Base MLB'!A:C,3,0)," ") -> 0.115 | F41: =IFERROR(C41/I41," ") -> 0.050866411 | G41: =IFERROR(MAX((ROUNDUP((E41-F41)*100,0)+0.5)/100,4.5%),"") -> 0.075 | H41: =IFERROR((ROUNDUP((E41-F41)*100,0)+0.5)/100,"") -> 0.075 | I41: ='Planilha CP Meli'!G6 -> 1985.2 | J41: =IFERROR(INDEX('Base com preços'!$C:$O,MATCH(B41,'Base com preços'!$A:$A,0),MATCH(G41,'Base com preços'!$C$1:$O$1,0)),IFERROR(INDEX('Boa forma'!$C:$O,MATCH(A41,'Boa forma'!$A:$A,0),MATCH(G41,'Boa forma'!$C$1:$O$1,0)),"")) -> 1811.849 | K41: =IFERROR(J41-I41," ") -> -173.35095 | L41: =IFERROR(IF(K41<0,"Sim",IF(I41>=J41*0.95,"Sim","Não")),"Não") -> Sim
A42: ='Planilha CP Meli'!B49 -> MLB3588170741 | B42: ='Planilha CP Meli'!C49 -> PA62750 | C42: ='Planilha CP Meli'!E49 -> 94.64 | D42: =IFERROR(VLOOKUP(A42,'Base MLB'!A:B,2,0)," ") -> Clássico | E42: =IFERROR(VLOOKUP(A42,'Base MLB'!A:C,3,0)," ") -> 0.115 | F42: =IFERROR(C42/I42," ") -> 0.08 | G42: =IFERROR(MAX((ROUNDUP((E42-F42)*100,0)+0.5)/100,4.5%),"") -> 0.045 | H42: =IFERROR((ROUNDUP((E42-F42)*100,0)+0.5)/100,"") -> 0.045 | I42: ='Planilha CP Meli'!G49 -> 1183 | J42: =IFERROR(INDEX('Base com preços'!$C:$O,MATCH(B42,'Base com preços'!$A:$A,0),MATCH(G42,'Base com preços'!$C$1:$O$1,0)),IFERROR(INDEX('Boa forma'!$C:$O,MATCH(A42,'Boa forma'!$A:$A,0),MATCH(G42,'Boa forma'!$C$1:$O$1,0)),"")) -> 1314.762 | K42: =IFERROR(J42-I42," ") -> 131.76201 | L42: =IFERROR(IF(K42<0,"Sim",IF(I42>=J42*0.95,"Sim","Não")),"Não") -> Não
A43: ='Planilha CP Meli'!B139 -> MLB4303878982 | B43: ='Planilha CP Meli'!C139 -> PA56275 | C43: ='Planilha CP Meli'!E139 -> 146.39 | D43: =IFERROR(VLOOKUP(A43,'Base MLB'!A:B,2,0)," ") -> Premium | E43: =IFERROR(VLOOKUP(A43,'Base MLB'!A:C,3,0)," ") -> 0.165 | F43: =IFERROR(C43/I43," ") -> 0.070043062 | G43: =IFERROR(MAX((ROUNDUP((E43-F43)*100,0)+0.5)/100,4.5%),"") -> 0.105 | H43: =IFERROR((ROUNDUP((E43-F43)*100,0)+0.5)/100,"") -> 0.105 | I43: ='Planilha CP Meli'!G139 -> 2090 | J43: =IFERROR(INDEX('Base com preços'!$C:$O,MATCH(B43,'Base com preços'!$A:$A,0),MATCH(G43,'Base com preços'!$C$1:$O$1,0)),IFERROR(INDEX('Boa forma'!$C:$O,MATCH(A43,'Boa forma'!$A:$A,0),MATCH(G43,'Boa forma'!$C$1:$O$1,0)),"")) -> 1961.5091 | K43: =IFERROR(J43-I43," ") -> -128.49094 | L43: =IFERROR(IF(K43<0,"Sim",IF(I43>=J43*0.95,"Sim","Não")),"Não") -> Sim
A44: ='Planilha CP Meli'!B7 -> MLB3473661733 | B44: ='Planilha CP Meli'!C7 -> PA85347 | C44: ='Planilha CP Meli'!E7 -> 87.92 | D44: =IFERROR(VLOOKUP(A44,'Base MLB'!A:B,2,0)," ") -> Clássico | E44: =IFERROR(VLOOKUP(A44,'Base MLB'!A:C,3,0)," ") -> 0.115 | F44: =IFERROR(C44/I44," ") -> 0.08 | G44: =IFERROR(MAX((ROUNDUP((E44-F44)*100,0)+0.5)/100,4.5%),"") -> 0.045 | H44: =IFERROR((ROUNDUP((E44-F44)*100,0)+0.5)/100,"") -> 0.045 | I44: ='Planilha CP Meli'!G7 -> 1099 | J44: =IFERROR(INDEX('Base com preços'!$C:$O,MATCH(B44,'Base com preços'!$A:$A,0),MATCH(G44,'Base com preços'!$C$1:$O$1,0)),IFERROR(INDEX('Boa forma'!$C:$O,MATCH(A44,'Boa forma'!$A:$A,0),MATCH(G44,'Boa forma'!$C$1:$O$1,0)),"")) -> 1260.9148 | K44: =IFERROR(J44-I44," ") -> 161.91482 | L44: =IFERROR(IF(K44<0,"Sim",IF(I44>=J44*0.95,"Sim","Não")),"Não") -> Não
A45: ='Planilha CP Meli'!B19 -> MLB3504972853 | B45: ='Planilha CP Meli'!C19 -> PA66793 | C45: ='Planilha CP Meli'!E19 -> 232.62 | D45: =IFERROR(VLOOKUP(A45,'Base MLB'!A:B,2,0)," ") -> Premium | E45: =IFERROR(VLOOKUP(A45,'Base MLB'!A:C,3,0)," ") -> 0.165 | F45: =IFERROR(C45/I45," ") -> 0.079997524 | G45: =IFERROR(MAX((ROUNDUP((E45-F45)*100,0)+0.5)/100,4.5%),"") -> 0.095 | H45: =IFERROR((ROUNDUP((E45-F45)*100,0)+0.5)/100,"") -> 0.095 | I45: ='Planilha CP Meli'!G19 -> 2907.84 | J45: =IFERROR(INDEX('Base com preços'!$C:$O,MATCH(B45,'Base com preços'!$A:$A,0),MATCH(G45,'Base com preços'!$C$1:$O$1,0)),IFERROR(INDEX('Boa forma'!$C:$O,MATCH(A45,'Boa forma'!$A:$A,0),MATCH(G45,'Boa forma'!$C$1:$O$1,0)),"")) -> 2820.6066 | K45: =IFERROR(J45-I45," ") -> -87.233414 | L45: =IFERROR(IF(K45<0,"Sim",IF(I45>=J45*0.95,"Sim","Não")),"Não") -> Sim
A46: ='Planilha CP Meli'!B146 -> MLB4343853346 | B46: ='Planilha CP Meli'!C146 -> PA85372 | C46: ='Planilha CP Meli'!E146 -> 232.92 | D46: =IFERROR(VLOOKUP(A46,'Base MLB'!A:B,2,0)," ") -> Clássico | E46: =IFERROR(VLOOKUP(A46,'Base MLB'!A:C,3,0)," ") -> 0.115 | F46: =IFERROR(C46/I46," ") -> 0.071500052 | G46: =IFERROR(MAX((ROUNDUP((E46-F46)*100,0)+0.5)/100,4.5%),"") -> 0.055 | H46: =IFERROR((ROUNDUP((E46-F46)*100,0)+0.5)/100,"") -> 0.055 | I46: ='Planilha CP Meli'!G146 -> 3257.62 | J46: =IFERROR(INDEX('Base com preços'!$C:$O,MATCH(B46,'Base com preços'!$A:$A,0),MATCH(G46,'Base com preços'!$C$1:$O$1,0)),IFERROR(INDEX('Boa forma'!$C:$O,MATCH(A46,'Boa forma'!$A:$A,0),MATCH(G46,'Boa forma'!$C$1:$O$1,0)),"")) -> 2797.4348 | K46: =IFERROR(J46-I46," ") -> -460.18516 | L46: =IFERROR(IF(K46<0,"Sim",IF(I46>=J46*0.95,"Sim","Não")),"Não") -> Sim
A47: ='Planilha CP Meli'!B42 -> MLB3570548313 | B47: ='Planilha CP Meli'!C42 -> PA52318 | C47: ='Planilha CP Meli'!E42 -> 124.55 | D47: =IFERROR(VLOOKUP(A47,'Base MLB'!A:B,2,0)," ") -> Clássico | E47: =IFERROR(VLOOKUP(A47,'Base MLB'!A:C,3,0)," ") -> 0.115 | F47: =IFERROR(C47/I47," ") -> 0.064123356 | G47: =IFERROR(MAX((ROUNDUP((E47-F47)*100,0)+0.5)/100,4.5%),"") -> 0.065 | H47: =IFERROR((ROUNDUP((E47-F47)*100,0)+0.5)/100,"") -> 0.065 | I47: ='Planilha CP Meli'!G42 -> 1942.35 | J47: =IFERROR(INDEX('Base com preços'!$C:$O,MATCH(B47,'Base com preços'!$A:$A,0),MATCH(G47,'Base com preços'!$C$1:$O$1,0)),IFERROR(INDEX('Boa forma'!$C:$O,MATCH(A47,'Boa forma'!$A:$A,0),MATCH(G47,'Boa forma'!$C$1:$O$1,0)),"")) -> 1719.5478 | K47: =IFERROR(J47-I47," ") -> -222.80218 | L47: =IFERROR(IF(K47<0,"Sim",IF(I47>=J47*0.95,"Sim","Não")),"Não") -> Sim
A48: ='Planilha CP Meli'!B24 -> MLB3523015145 | B48: ='Planilha CP Meli'!C24 -> PA66792 | C48: ='Planilha CP Meli'!E24 -> 92.93 | D48: =IFERROR(VLOOKUP(A48,'Base MLB'!A:B,2,0)," ") -> Clássico | E48: =IFERROR(VLOOKUP(A48,'Base MLB'!A:C,3,0)," ") -> 0.115 | F48: =IFERROR(C48/I48," ") -> 0.046777709 | G48: =IFERROR(MAX((ROUNDUP((E48-F48)*100,0)+0.5)/100,4.5%),"") -> 0.075 | H48: =IFERROR((ROUNDUP((E48-F48)*100,0)+0.5)/100,"") -> 0.075 | I48: ='Planilha CP Meli'!G24 -> 1986.63 | J48: =IFERROR(INDEX('Base com preços'!$C:$O,MATCH(B48,'Base com preços'!$A:$A,0),MATCH(G48,'Base com preços'!$C$1:$O$1,0)),IFERROR(INDEX('Boa forma'!$C:$O,MATCH(A48,'Boa forma'!$A:$A,0),MATCH(G48,'Boa forma'!$C$1:$O$1,0)),"")) -> 1813.1504 | K48: =IFERROR(J48-I48," ") -> -173.47959 | L48: =IFERROR(IF(K48<0,"Sim",IF(I48>=J48*0.95,"Sim","Não")),"Não") -> Sim
A49: ='Planilha CP Meli'!B35 -> MLB3551598189 | B49: ='Planilha CP Meli'!C35 -> PA62218 | C49: ='Planilha CP Meli'!E35 -> 91.81 | D49: =IFERROR(VLOOKUP(A49,'Base MLB'!A:B,2,0)," ") -> Premium | E49: =IFERROR(VLOOKUP(A49,'Base MLB'!A:C,3,0)," ") -> 0.165 | F49: =IFERROR(C49/I49," ") -> 0.07999756 | G49: =IFERROR(MAX((ROUNDUP((E49-F49)*100,0)+0.5)/100,4.5%),"") -> 0.095 | H49: =IFERROR((ROUNDUP((E49-F49)*100,0)+0.5)/100,"") -> 0.095 | I49: ='Planilha CP Meli'!G35 -> 1147.66 | J49: =IFERROR(INDEX('Base com preços'!$C:$O,MATCH(B49,'Base com preços'!$A:$A,0),MATCH(G49,'Base com preços'!$C$1:$O$1,0)),IFERROR(INDEX('Boa forma'!$C:$O,MATCH(A49,'Boa forma'!$A:$A,0),MATCH(G49,'Boa forma'!$C$1:$O$1,0)),"")) -> 1113.2335 | K49: =IFERROR(J49-I49," ") -> -34.426511 | L49: =IFERROR(IF(K49<0,"Sim",IF(I49>=J49*0.95,"Sim","Não")),"Não") -> Sim
A50: ='Planilha CP Meli'!B34 -> MLB3551585553 | B50: ='Planilha CP Meli'!C34 -> PA62215 | C50: ='Planilha CP Meli'!E34 -> 52.73 | D50: =IFERROR(VLOOKUP(A50,'Base MLB'!A:B,2,0)," ") -> Premium | E50: =IFERROR(VLOOKUP(A50,'Base MLB'!A:C,3,0)," ") -> 0.165 | F50: =IFERROR(C50/I50," ") -> 0.069993098 | G50: =IFERROR(MAX((ROUNDUP((E50-F50)*100,0)+0.5)/100,4.5%),"") -> 0.105 | H50: =IFERROR((ROUNDUP((E50-F50)*100,0)+0.5)/100,"") -> 0.105 | I50: ='Planilha CP Meli'!G34 -> 753.36 | J50: =IFERROR(INDEX('Base com preços'!$C:$O,MATCH(B50,'Base com preços'!$A:$A,0),MATCH(G50,'Base com preços'!$C$1:$O$1,0)),IFERROR(INDEX('Boa forma'!$C:$O,MATCH(A50,'Boa forma'!$A:$A,0),MATCH(G50,'Boa forma'!$C$1:$O$1,0)),"")) -> 753.35683 | K50: =IFERROR(J50-I50," ") -> -0.003166096 | L50: =IFERROR(IF(K50<0,"Sim",IF(I50>=J50*0.95,"Sim","Não")),"Não") -> Sim
A51: ='Planilha CP Meli'!B32 -> MLB3551550249 | B51: ='Planilha CP Meli'!C32 -> PA56216 | C51: ='Planilha CP Meli'!E32 -> 164.04 | D51: =IFERROR(VLOOKUP(A51,'Base MLB'!A:B,2,0)," ") -> Premium | E51: =IFERROR(VLOOKUP(A51,'Base MLB'!A:C,3,0)," ") -> 0.165 | F51: =IFERROR(C51/I51," ") -> 0.052653541 | G51: =IFERROR(MAX((ROUNDUP((E51-F51)*100,0)+0.5)/100,4.5%),"") -> 0.125 | H51: =IFERROR((ROUNDUP((E51-F51)*100,0)+0.5)/100,"") -> 0.125 | I51: ='Planilha CP Meli'!G32 -> 3115.46 | J51: =IFERROR(INDEX('Base com preços'!$C:$O,MATCH(B51,'Base com preços'!$A:$A,0),MATCH(G51,'Base com preços'!$C$1:$O$1,0)),IFERROR(INDEX('Boa forma'!$C:$O,MATCH(A51,'Boa forma'!$A:$A,0),MATCH(G51,'Boa forma'!$C$1:$O$1,0)),"")) -> 2843.3965 | K51: =IFERROR(J51-I51," ") -> -272.06349 | L51: =IFERROR(IF(K51<0,"Sim",IF(I51>=J51*0.95,"Sim","Não")),"Não") -> Sim
A52: ='Planilha CP Meli'!B127 -> MLB4263803583 | B52: ='Planilha CP Meli'!C127 -> PA56274 | C52: ='Planilha CP Meli'!E127 -> 114.45 | D52: =IFERROR(VLOOKUP(A52,'Base MLB'!A:B,2,0)," ") -> Premium | E52: =IFERROR(VLOOKUP(A52,'Base MLB'!A:C,3,0)," ") -> 0.165 | F52: =IFERROR(C52/I52," ") -> 0.07999972 | G52: =IFERROR(MAX((ROUNDUP((E52-F52)*100,0)+0.5)/100,4.5%),"") -> 0.095 | H52: =IFERROR((ROUNDUP((E52-F52)*100,0)+0.5)/100,"") -> 0.095 | I52: ='Planilha CP Meli'!G127 -> 1430.63 | J52: =IFERROR(INDEX('Base com preços'!$C:$O,MATCH(B52,'Base com preços'!$A:$A,0),MATCH(G52,'Base com preços'!$C$1:$O$1,0)),IFERROR(INDEX('Boa forma'!$C:$O,MATCH(A52,'Boa forma'!$A:$A,0),MATCH(G52,'Boa forma'!$C$1:$O$1,0)),"")) -> 1387.7114 | K52: =IFERROR(J52-I52," ") -> -42.918554 | L52: =IFERROR(IF(K52<0,"Sim",IF(I52>=J52*0.95,"Sim","Não")),"Não") -> Sim
A53: ='Planilha CP Meli'!B8 -> MLB3473786083 | B53: ='Planilha CP Meli'!C8 -> PA85368 | C53: ='Planilha CP Meli'!E8 -> 238.24 | D53: =IFERROR(VLOOKUP(A53,'Base MLB'!A:B,2,0)," ") -> Clássico | E53: =IFERROR(VLOOKUP(A53,'Base MLB'!A:C,3,0)," ") -> 0.115 | F53: =IFERROR(C53/I53," ") -> 0.08 | G53: =IFERROR(MAX((ROUNDUP((E53-F53)*100,0)+0.5)/100,4.5%),"") -> 0.045 | H53: =IFERROR((ROUNDUP((E53-F53)*100,0)+0.5)/100,"") -> 0.045 | I53: ='Planilha CP Meli'!G8 -> 2978 | J53: =IFERROR(INDEX('Base com preços'!$C:$O,MATCH(B53,'Base com preços'!$A:$A,0),MATCH(G53,'Base com preços'!$C$1:$O$1,0)),IFERROR(INDEX('Boa forma'!$C:$O,MATCH(A53,'Boa forma'!$A:$A,0),MATCH(G53,'Boa forma'!$C$1:$O$1,0)),"")) -> 2978.7967 | K53: =IFERROR(J53-I53," ") -> 0.7966584 | L53: =IFERROR(IF(K53<0,"Sim",IF(I53>=J53*0.95,"Sim","Não")),"Não") -> Sim
A54: ='Planilha CP Meli'!B23 -> MLB3523015077 | B54: ='Planilha CP Meli'!C23 -> PA66731 | C54: ='Planilha CP Meli'!E23 -> 179.15 | D54: =IFERROR(VLOOKUP(A54,'Base MLB'!A:B,2,0)," ") -> Premium | E54: =IFERROR(VLOOKUP(A54,'Base MLB'!A:C,3,0)," ") -> 0.165 | F54: =IFERROR(C54/I54," ") -> 0.051283446 | G54: =IFERROR(MAX((ROUNDUP((E54-F54)*100,0)+0.5)/100,4.5%),"") -> 0.125 | H54: =IFERROR((ROUNDUP((E54-F54)*100,0)+0.5)/100,"") -> 0.125 | I54: ='Planilha CP Meli'!G23 -> 3493.33 | J54: =IFERROR(INDEX('Base com preços'!$C:$O,MATCH(B54,'Base com preços'!$A:$A,0),MATCH(G54,'Base com preços'!$C$1:$O$1,0)),IFERROR(INDEX('Boa forma'!$C:$O,MATCH(A54,'Boa forma'!$A:$A,0),MATCH(G54,'Boa forma'!$C$1:$O$1,0)),"")) -> 3188.2701 | K54: =IFERROR(J54-I54," ") -> -305.0599 | L54: =IFERROR(IF(K54<0,"Sim",IF(I54>=J54*0.95,"Sim","Não")),"Não") -> Sim
A55: ='Planilha CP Meli'!B25 -> MLB3537447705 | B55: ='Planilha CP Meli'!C25 -> PA85372 | C55: ='Planilha CP Meli'!E25 -> 260.61 | D55: =IFERROR(VLOOKUP(A55,'Base MLB'!A:B,2,0)," ") -> Premium | E55: =IFERROR(VLOOKUP(A55,'Base MLB'!A:C,3,0)," ") -> 0.165 | F55: =IFERROR(C55/I55," ") -> 0.079999877 | G55: =IFERROR(MAX((ROUNDUP((E55-F55)*100,0)+0.5)/100,4.5%),"") -> 0.095 | H55: =IFERROR((ROUNDUP((E55-F55)*100,0)+0.5)/100,"") -> 0.095 | I55: ='Planilha CP Meli'!G25 -> 3257.63 | J55: =IFERROR(INDEX('Base com preços'!$C:$O,MATCH(B55,'Base com preços'!$A:$A,0),MATCH(G55,'Base com preços'!$C$1:$O$1,0)),IFERROR(INDEX('Boa forma'!$C:$O,MATCH(A55,'Boa forma'!$A:$A,0),MATCH(G55,'Boa forma'!$C$1:$O$1,0)),"")) -> 3159.8978 | K55: =IFERROR(J55-I55," ") -> -97.73216 | L55: =IFERROR(IF(K55<0,"Sim",IF(I55>=J55*0.95,"Sim","Não")),"Não") -> Sim
A56: ='Planilha CP Meli'!B216 -> MLB5294260782 | B56: ='Planilha CP Meli'!C216 -> PA35622 | C56: ='Planilha CP Meli'!E216 -> 137.02 | D56: =IFERROR(VLOOKUP(A56,'Base MLB'!A:B,2,0)," ") -> Clássico | E56: =IFERROR(VLOOKUP(A56,'Base MLB'!A:C,3,0)," ") -> 0.115 | F56: =IFERROR(C56/I56," ") -> 0.060449911 | G56: =IFERROR(MAX((ROUNDUP((E56-F56)*100,0)+0.5)/100,4.5%),"") -> 0.065 | H56: =IFERROR((ROUNDUP((E56-F56)*100,0)+0.5)/100,"") -> 0.065 | I56: ='Planilha CP Meli'!G216 -> 2266.67 | J56: =IFERROR(INDEX('Base com preços'!$C:$O,MATCH(B56,'Base com preços'!$A:$A,0),MATCH(G56,'Base com preços'!$C$1:$O$1,0)),IFERROR(INDEX('Boa forma'!$C:$O,MATCH(A56,'Boa forma'!$A:$A,0),MATCH(G56,'Boa forma'!$C$1:$O$1,0)),"")) -> 2006.6656 | K56: =IFERROR(J56-I56," ") -> -260.00438 | L56: =IFERROR(IF(K56<0,"Sim",IF(I56>=J56*0.95,"Sim","Não")),"Não") -> Sim
A57: ='Planilha CP Meli'!B232 -> MLB5459749696 | B57: ='Planilha CP Meli'!C232 -> PA94829 | C57: ='Planilha CP Meli'!E232 -> 136.27 | D57: =IFERROR(VLOOKUP(A57,'Base MLB'!A:B,2,0)," ") -> Clássico | E57: =IFERROR(VLOOKUP(A57,'Base MLB'!A:C,3,0)," ") -> 0.115 | F57: =IFERROR(C57/I57," ") -> 0.079998826 | G57: =IFERROR(MAX((ROUNDUP((E57-F57)*100,0)+0.5)/100,4.5%),"") -> 0.045 | H57: =IFERROR((ROUNDUP((E57-F57)*100,0)+0.5)/100,"") -> 0.045 | I57: ='Planilha CP Meli'!G232 -> 1703.4 | J57: =IFERROR(INDEX('Base com preços'!$C:$O,MATCH(B57,'Base com preços'!$A:$A,0),MATCH(G57,'Base com preços'!$C$1:$O$1,0)),IFERROR(INDEX('Boa forma'!$C:$O,MATCH(A57,'Boa forma'!$A:$A,0),MATCH(G57,'Boa forma'!$C$1:$O$1,0)),"")) -> 1418.8873 | K57: =IFERROR(J57-I57," ") -> -284.51273 | L57: =IFERROR(IF(K57<0,"Sim",IF(I57>=J57*0.95,"Sim","Não")),"Não") -> Sim
A58: ='Planilha CP Meli'!B14 -> MLB3474584357 | B58: ='Planilha CP Meli'!C14 -> PA85361 | C58: ='Planilha CP Meli'!E14 -> 202.96 | D58: =IFERROR(VLOOKUP(A58,'Base MLB'!A:B,2,0)," ") -> Premium | E58: =IFERROR(VLOOKUP(A58,'Base MLB'!A:C,3,0)," ") -> 0.165 | F58: =IFERROR(C58/I58," ") -> 0.073080538 | G58: =IFERROR(MAX((ROUNDUP((E58-F58)*100,0)+0.5)/100,4.5%),"") -> 0.105 | H58: =IFERROR((ROUNDUP((E58-F58)*100,0)+0.5)/100,"") -> 0.105 | I58: ='Planilha CP Meli'!G14 -> 2777.21 | J58: =IFERROR(INDEX('Base com preços'!$C:$O,MATCH(B58,'Base com preços'!$A:$A,0),MATCH(G58,'Base com preços'!$C$1:$O$1,0)),IFERROR(INDEX('Boa forma'!$C:$O,MATCH(A58,'Boa forma'!$A:$A,0),MATCH(G58,'Boa forma'!$C$1:$O$1,0)),"")) -> 2384.8879 | K58: =IFERROR(J58-I58," ") -> -392.32212 | L58: =IFERROR(IF(K58<0,"Sim",IF(I58>=J58*0.95,"Sim","Não")),"Não") -> Sim
A59: ='Planilha CP Meli'!B13 -> MLB3474583509 | B59: ='Planilha CP Meli'!C13 -> PA85371 | C59: ='Planilha CP Meli'!E13 -> 211.27 | D59: =IFERROR(VLOOKUP(A59,'Base MLB'!A:B,2,0)," ") -> Premium | E59: =IFERROR(VLOOKUP(A59,'Base MLB'!A:C,3,0)," ") -> 0.165 | F59: =IFERROR(C59/I59," ") -> 0.07999894 | G59: =IFERROR(MAX((ROUNDUP((E59-F59)*100,0)+0.5)/100,4.5%),"") -> 0.095 | H59: =IFERROR((ROUNDUP((E59-F59)*100,0)+0.5)/100,"") -> 0.095 | I59: ='Planilha CP Meli'!G13 -> 2640.91 | J59: =IFERROR(INDEX('Base com preços'!$C:$O,MATCH(B59,'Base com preços'!$A:$A,0),MATCH(G59,'Base com preços'!$C$1:$O$1,0)),IFERROR(INDEX('Boa forma'!$C:$O,MATCH(A59,'Boa forma'!$A:$A,0),MATCH(G59,'Boa forma'!$C$1:$O$1,0)),"")) -> 2561.6813 | K59: =IFERROR(J59-I59," ") -> -79.228714 | L59: =IFERROR(IF(K59<0,"Sim",IF(I59>=J59*0.95,"Sim","Não")),"Não") -> Sim
A60: ='Planilha CP Meli'!B133 -> MLB4297684784 | B60: ='Planilha CP Meli'!C133 -> PA69847 | C60: ='Planilha CP Meli'!E133 -> 110.88 | D60: =IFERROR(VLOOKUP(A60,'Base MLB'!A:B,2,0)," ") -> Premium | E60: =IFERROR(VLOOKUP(A60,'Base MLB'!A:C,3,0)," ") -> 0.165 | F60: =IFERROR(C60/I60," ") -> 0.08 | G60: =IFERROR(MAX((ROUNDUP((E60-F60)*100,0)+0.5)/100,4.5%),"") -> 0.095 | H60: =IFERROR((ROUNDUP((E60-F60)*100,0)+0.5)/100,"") -> 0.095 | I60: ='Planilha CP Meli'!G133 -> 1386 | J60: =IFERROR(INDEX('Base com preços'!$C:$O,MATCH(B60,'Base com preços'!$A:$A,0),MATCH(G60,'Base com preços'!$C$1:$O$1,0)),IFERROR(INDEX('Boa forma'!$C:$O,MATCH(A60,'Boa forma'!$A:$A,0),MATCH(G60,'Boa forma'!$C$1:$O$1,0)),"")) -> 1385.9808 | K60: =IFERROR(J60-I60," ") -> -0.019171139 | L60: =IFERROR(IF(K60<0,"Sim",IF(I60>=J60*0.95,"Sim","Não")),"Não") -> Sim
A61: ='Planilha CP Meli'!B33 -> MLB3551572499 | B61: ='Planilha CP Meli'!C33 -> PA37608 | C61: ='Planilha CP Meli'!E33 -> 103.11 | D61: =IFERROR(VLOOKUP(A61,'Base MLB'!A:B,2,0)," ") -> Premium | E61: =IFERROR(VLOOKUP(A61,'Base MLB'!A:C,3,0)," ") -> 0.165 | F61: =IFERROR(C61/I61," ") -> 0.079993483 | G61: =IFERROR(MAX((ROUNDUP((E61-F61)*100,0)+0.5)/100,4.5%),"") -> 0.095 | H61: =IFERROR((ROUNDUP((E61-F61)*100,0)+0.5)/100,"") -> 0.095 | I61: ='Planilha CP Meli'!G33 -> 1288.98 | J61: =IFERROR(INDEX('Base com preços'!$C:$O,MATCH(B61,'Base com preços'!$A:$A,0),MATCH(G61,'Base com preços'!$C$1:$O$1,0)),IFERROR(INDEX('Boa forma'!$C:$O,MATCH(A61,'Boa forma'!$A:$A,0),MATCH(G61,'Boa forma'!$C$1:$O$1,0)),"")) -> 1250.3091 | K61: =IFERROR(J61-I61," ") -> -38.670864 | L61: =IFERROR(IF(K61<0,"Sim",IF(I61>=J61*0.95,"Sim","Não")),"Não") -> Sim
A62: ='Planilha CP Meli'!B56 -> MLB3595883579 | B62: ='Planilha CP Meli'!C56 -> PA62582 | C62: ='Planilha CP Meli'!E56 -> 53.13 | D62: =IFERROR(VLOOKUP(A62,'Base MLB'!A:B,2,0)," ") -> Clássico | E62: =IFERROR(VLOOKUP(A62,'Base MLB'!A:C,3,0)," ") -> 0.115 | F62: =IFERROR(C62/I62," ") -> 0.042177378 | G62: =IFERROR(MAX((ROUNDUP((E62-F62)*100,0)+0.5)/100,4.5%),"") -> 0.085 | H62: =IFERROR((ROUNDUP((E62-F62)*100,0)+0.5)/100,"") -> 0.085 | I62: ='Planilha CP Meli'!G56 -> 1259.68 | J62: =IFERROR(INDEX('Base com preços'!$C:$O,MATCH(B62,'Base com preços'!$A:$A,0),MATCH(G62,'Base com preços'!$C$1:$O$1,0)),IFERROR(INDEX('Boa forma'!$C:$O,MATCH(A62,'Boa forma'!$A:$A,0),MATCH(G62,'Boa forma'!$C$1:$O$1,0)),"")) -> 1185.2352 | K62: =IFERROR(J62-I62," ") -> -74.444817 | L62: =IFERROR(IF(K62<0,"Sim",IF(I62>=J62*0.95,"Sim","Não")),"Não") -> Sim
A63: ='Planilha CP Meli'!B226 -> MLB5418076938 | B63: ='Planilha CP Meli'!C226 -> PA52128 | C63: ='Planilha CP Meli'!E226 -> 35.91 | D63: =IFERROR(VLOOKUP(A63,'Base MLB'!A:B,2,0)," ") -> Premium | E63: =IFERROR(VLOOKUP(A63,'Base MLB'!A:C,3,0)," ") -> 0.165 | F63: =IFERROR(C63/I63," ") -> 0.069995907 | G63: =IFERROR(MAX((ROUNDUP((E63-F63)*100,0)+0.5)/100,4.5%),"") -> 0.105 | H63: =IFERROR((ROUNDUP((E63-F63)*100,0)+0.5)/100,"") -> 0.105 | I63: ='Planilha CP Meli'!G226 -> 513.03 | J63: =IFERROR(INDEX('Base com preços'!$C:$O,MATCH(B63,'Base com preços'!$A:$A,0),MATCH(G63,'Base com preços'!$C$1:$O$1,0)),IFERROR(INDEX('Boa forma'!$C:$O,MATCH(A63,'Boa forma'!$A:$A,0),MATCH(G63,'Boa forma'!$C$1:$O$1,0)),"")) -> 513.03012 | K63: =IFERROR(J63-I63," ") -> 0.00012334619 | L63: =IFERROR(IF(K63<0,"Sim",IF(I63>=J63*0.95,"Sim","Não")),"Não") -> Sim
A64: ='Planilha CP Meli'!B248 -> MLB5831854476 | B64: ='Planilha CP Meli'!C248 -> PA33103 | C64: ='Planilha CP Meli'!E248 -> 174.18 | D64: =IFERROR(VLOOKUP(A64,'Base MLB'!A:B,2,0)," ") -> Clássico | E64: =IFERROR(VLOOKUP(A64,'Base MLB'!A:C,3,0)," ") -> 0.115 | F64: =IFERROR(C64/I64," ") -> 0.05485846 | G64: =IFERROR(MAX((ROUNDUP((E64-F64)*100,0)+0.5)/100,4.5%),"") -> 0.075 | H64: =IFERROR((ROUNDUP((E64-F64)*100,0)+0.5)/100,"") -> 0.075 | I64: ='Planilha CP Meli'!G248 -> 3175.08 | J64: =IFERROR(INDEX('Base com preços'!$C:$O,MATCH(B64,'Base com preços'!$A:$A,0),MATCH(G64,'Base com preços'!$C$1:$O$1,0)),IFERROR(INDEX('Boa forma'!$C:$O,MATCH(A64,'Boa forma'!$A:$A,0),MATCH(G64,'Boa forma'!$C$1:$O$1,0)),"")) -> 2897.8193 | K64: =IFERROR(J64-I64," ") -> -277.26071 | L64: =IFERROR(IF(K64<0,"Sim",IF(I64>=J64*0.95,"Sim","Não")),"Não") -> Sim
A65: ='Planilha CP Meli'!B18 -> MLB3504947943 | B65: ='Planilha CP Meli'!C18 -> PA66721 | C65: ='Planilha CP Meli'!E18 -> 106.48 | D65: =IFERROR(VLOOKUP(A65,'Base MLB'!A:B,2,0)," ") -> Premium | E65: =IFERROR(VLOOKUP(A65,'Base MLB'!A:C,3,0)," ") -> 0.165 | F65: =IFERROR(C65/I65," ") -> 0.08 | G65: =IFERROR(MAX((ROUNDUP((E65-F65)*100,0)+0.5)/100,4.5%),"") -> 0.095 | H65: =IFERROR((ROUNDUP((E65-F65)*100,0)+0.5)/100,"") -> 0.095 | I65: ='Planilha CP Meli'!G18 -> 1331 | J65: =IFERROR(INDEX('Base com preços'!$C:$O,MATCH(B65,'Base com preços'!$A:$A,0),MATCH(G65,'Base com preços'!$C$1:$O$1,0)),IFERROR(INDEX('Boa forma'!$C:$O,MATCH(A65,'Boa forma'!$A:$A,0),MATCH(G65,'Boa forma'!$C$1:$O$1,0)),"")) -> 1330.9556 | K65: =IFERROR(J65-I65," ") -> -0.044446306 | L65: =IFERROR(IF(K65<0,"Sim",IF(I65>=J65*0.95,"Sim","Não")),"Não") -> Sim
A66: ='Planilha CP Meli'!B27 -> MLB3542974939 | B66: ='Planilha CP Meli'!C27 -> PA35620 | C66: ='Planilha CP Meli'!E27 -> 150.1 | D66: =IFERROR(VLOOKUP(A66,'Base MLB'!A:B,2,0)," ") -> Premium | E66: =IFERROR(VLOOKUP(A66,'Base MLB'!A:C,3,0)," ") -> 0.165 | F66: =IFERROR(C66/I66," ") -> 0.079996163 | G66: =IFERROR(MAX((ROUNDUP((E66-F66)*100,0)+0.5)/100,4.5%),"") -> 0.095 | H66: =IFERROR((ROUNDUP((E66-F66)*100,0)+0.5)/100,"") -> 0.095 | I66: ='Planilha CP Meli'!G27 -> 1876.34 | J66: =IFERROR(INDEX('Base com preços'!$C:$O,MATCH(B66,'Base com preços'!$A:$A,0),MATCH(G66,'Base com preços'!$C$1:$O$1,0)),IFERROR(INDEX('Boa forma'!$C:$O,MATCH(A66,'Boa forma'!$A:$A,0),MATCH(G66,'Boa forma'!$C$1:$O$1,0)),"")) -> 1820.0529 | K66: =IFERROR(J66-I66," ") -> -56.287107 | L66: =IFERROR(IF(K66<0,"Sim",IF(I66>=J66*0.95,"Sim","Não")),"Não") -> Sim
A67: ='Planilha CP Meli'!B28 -> MLB3543015545 | B67: ='Planilha CP Meli'!C28 -> PA56211 | C67: ='Planilha CP Meli'!E28 -> 117.06 | D67: =IFERROR(VLOOKUP(A67,'Base MLB'!A:B,2,0)," ") -> Premium | E67: =IFERROR(VLOOKUP(A67,'Base MLB'!A:C,3,0)," ") -> 0.165 | F67: =IFERROR(C67/I67," ") -> 0.078499484 | G67: =IFERROR(MAX((ROUNDUP((E67-F67)*100,0)+0.5)/100,4.5%),"") -> 0.095 | H67: =IFERROR((ROUNDUP((E67-F67)*100,0)+0.5)/100,"") -> 0.095 | I67: ='Planilha CP Meli'!G28 -> 1491.22 | J67: =IFERROR(INDEX('Base com preços'!$C:$O,MATCH(B67,'Base com preços'!$A:$A,0),MATCH(G67,'Base com preços'!$C$1:$O$1,0)),IFERROR(INDEX('Boa forma'!$C:$O,MATCH(A67,'Boa forma'!$A:$A,0),MATCH(G67,'Boa forma'!$C$1:$O$1,0)),"")) -> 1446.4829 | K67: =IFERROR(J67-I67," ") -> -44.737084 | L67: =IFERROR(IF(K67<0,"Sim",IF(I67>=J67*0.95,"Sim","Não")),"Não") -> Sim
A68: ='Planilha CP Meli'!B59 -> MLB3595899773 | B68: ='Planilha CP Meli'!C59 -> PA09771 | C68: ='Planilha CP Meli'!E59 -> 98.55 | D68: =IFERROR(VLOOKUP(A68,'Base MLB'!A:B,2,0)," ") -> Clássico | E68: =IFERROR(VLOOKUP(A68,'Base MLB'!A:C,3,0)," ") -> 0.115 | F68: =IFERROR(C68/I68," ") -> 0.079999026 | G68: =IFERROR(MAX((ROUNDUP((E68-F68)*100,0)+0.5)/100,4.5%),"") -> 0.045 | H68: =IFERROR((ROUNDUP((E68-F68)*100,0)+0.5)/100,"") -> 0.045 | I68: ='Planilha CP Meli'!G59 -> 1231.89 | J68: =IFERROR(INDEX('Base com preços'!$C:$O,MATCH(B68,'Base com preços'!$A:$A,0),MATCH(G68,'Base com preços'!$C$1:$O$1,0)),IFERROR(INDEX('Boa forma'!$C:$O,MATCH(A68,'Boa forma'!$A:$A,0),MATCH(G68,'Boa forma'!$C$1:$O$1,0)),"")) -> 1026.1321 | K68: =IFERROR(J68-I68," ") -> -205.75785 | L68: =IFERROR(IF(K68<0,"Sim",IF(I68>=J68*0.95,"Sim","Não")),"Não") -> Sim
A69: ='Planilha CP Meli'!B45 -> MLB3570611105 | B69: ='Planilha CP Meli'!C45 -> PA67503 | C69: ='Planilha CP Meli'!E45 -> 69.63 | D69: =IFERROR(VLOOKUP(A69,'Base MLB'!A:B,2,0)," ") -> Clássico | E69: =IFERROR(VLOOKUP(A69,'Base MLB'!A:C,3,0)," ") -> 0.115 | F69: =IFERROR(C69/I69," ") -> 0.052605733 | G69: =IFERROR(MAX((ROUNDUP((E69-F69)*100,0)+0.5)/100,4.5%),"") -> 0.075 | H69: =IFERROR((ROUNDUP((E69-F69)*100,0)+0.5)/100,"") -> 0.075 | I69: ='Planilha CP Meli'!G45 -> 1323.62 | J69: =IFERROR(INDEX('Base com preços'!$C:$O,MATCH(B69,'Base com preços'!$A:$A,0),MATCH(G69,'Base com preços'!$C$1:$O$1,0)),IFERROR(INDEX('Boa forma'!$C:$O,MATCH(A69,'Boa forma'!$A:$A,0),MATCH(G69,'Boa forma'!$C$1:$O$1,0)),"")) -> 1208.0394 | K69: =IFERROR(J69-I69," ") -> -115.58061 | L69: =IFERROR(IF(K69<0,"Sim",IF(I69>=J69*0.95,"Sim","Não")),"Não") -> Sim
A70: ='Planilha CP Meli'!B63 -> MLB3595912439 | B70: ='Planilha CP Meli'!C63 -> PA66406 | C70: ='Planilha CP Meli'!E63 -> 80.55 | D70: =IFERROR(VLOOKUP(A70,'Base MLB'!A:B,2,0)," ") -> Clássico | E70: =IFERROR(VLOOKUP(A70,'Base MLB'!A:C,3,0)," ") -> 0.115 | F70: =IFERROR(C70/I70," ") -> 0.06972034 | G70: =IFERROR(MAX((ROUNDUP((E70-F70)*100,0)+0.5)/100,4.5%),"") -> 0.055 | H70: =IFERROR((ROUNDUP((E70-F70)*100,0)+0.5)/100,"") -> 0.055 | I70: ='Planilha CP Meli'!G63 -> 1155.33 | J70: =IFERROR(INDEX('Base com preços'!$C:$O,MATCH(B70,'Base com preços'!$A:$A,0),MATCH(G70,'Base com preços'!$C$1:$O$1,0)),IFERROR(INDEX('Boa forma'!$C:$O,MATCH(A70,'Boa forma'!$A:$A,0),MATCH(G70,'Boa forma'!$C$1:$O$1,0)),"")) -> 992.12568 | K70: =IFERROR(J70-I70," ") -> -163.20432 | L70: =IFERROR(IF(K70<0,"Sim",IF(I70>=J70*0.95,"Sim","Não")),"Não") -> Sim
A71: ='Planilha CP Meli'!B39 -> MLB3569812971 | B71: ='Planilha CP Meli'!C39 -> PA67503 | C71: ='Planilha CP Meli'!E39 -> 97.53 | D71: =IFERROR(VLOOKUP(A71,'Base MLB'!A:B,2,0)," ") -> Premium | E71: =IFERROR(VLOOKUP(A71,'Base MLB'!A:C,3,0)," ") -> 0.165 | F71: =IFERROR(C71/I71," ") -> 0.073683733 | G71: =IFERROR(MAX((ROUNDUP((E71-F71)*100,0)+0.5)/100,4.5%),"") -> 0.105 | H71: =IFERROR((ROUNDUP((E71-F71)*100,0)+0.5)/100,"") -> 0.105 | I71: ='Planilha CP Meli'!G39 -> 1323.63 | J71: =IFERROR(INDEX('Base com preços'!$C:$O,MATCH(B71,'Base com preços'!$A:$A,0),MATCH(G71,'Base com preços'!$C$1:$O$1,0)),IFERROR(INDEX('Boa forma'!$C:$O,MATCH(A71,'Boa forma'!$A:$A,0),MATCH(G71,'Boa forma'!$C$1:$O$1,0)),"")) -> 1323.6278 | K71: =IFERROR(J71-I71," ") -> -0.0021661548 | L71: =IFERROR(IF(K71<0,"Sim",IF(I71>=J71*0.95,"Sim","Não")),"Não") -> Sim
A72: ='Planilha CP Meli'!B66 -> MLB3595937931 | B72: ='Planilha CP Meli'!C66 -> PA56211 | C72: ='Planilha CP Meli'!E66 -> 102.4 | D72: =IFERROR(VLOOKUP(A72,'Base MLB'!A:B,2,0)," ") -> Clássico | E72: =IFERROR(VLOOKUP(A72,'Base MLB'!A:C,3,0)," ") -> 0.115 | F72: =IFERROR(C72/I72," ") -> 0.08 | G72: =IFERROR(MAX((ROUNDUP((E72-F72)*100,0)+0.5)/100,4.5%),"") -> 0.045 | H72: =IFERROR((ROUNDUP((E72-F72)*100,0)+0.5)/100,"") -> 0.045 | I72: ='Planilha CP Meli'!G66 -> 1280 | J72: =IFERROR(INDEX('Base com preços'!$C:$O,MATCH(B72,'Base com preços'!$A:$A,0),MATCH(G72,'Base com preços'!$C$1:$O$1,0)),IFERROR(INDEX('Boa forma'!$C:$O,MATCH(A72,'Boa forma'!$A:$A,0),MATCH(G72,'Boa forma'!$C$1:$O$1,0)),"")) -> 1242.1441 | K72: =IFERROR(J72-I72," ") -> -37.855903 | L72: =IFERROR(IF(K72<0,"Sim",IF(I72>=J72*0.95,"Sim","Não")),"Não") -> Sim
A73: ='Planilha CP Meli'!B52 -> MLB3595836489 | B73: ='Planilha CP Meli'!C52 -> PA56267 | C73: ='Planilha CP Meli'!E52 -> 96.67 | D73: =IFERROR(VLOOKUP(A73,'Base MLB'!A:B,2,0)," ") -> Premium | E73: =IFERROR(VLOOKUP(A73,'Base MLB'!A:C,3,0)," ") -> 0.165 | F73: =IFERROR(C73/I73," ") -> 0.079995697 | G73: =IFERROR(MAX((ROUNDUP((E73-F73)*100,0)+0.5)/100,4.5%),"") -> 0.095 | H73: =IFERROR((ROUNDUP((E73-F73)*100,0)+0.5)/100,"") -> 0.095 | I73: ='Planilha CP Meli'!G52 -> 1208.44 | J73: =IFERROR(INDEX('Base com preços'!$C:$O,MATCH(B73,'Base com preços'!$A:$A,0),MATCH(G73,'Base com preços'!$C$1:$O$1,0)),IFERROR(INDEX('Boa forma'!$C:$O,MATCH(A73,'Boa forma'!$A:$A,0),MATCH(G73,'Boa forma'!$C$1:$O$1,0)),"")) -> 1172.1836 | K73: =IFERROR(J73-I73," ") -> -36.256378 | L73: =IFERROR(IF(K73<0,"Sim",IF(I73>=J73*0.95,"Sim","Não")),"Não") -> Sim
A74: ='Planilha CP Meli'!B106 -> MLB4111791123 | B74: ='Planilha CP Meli'!C106 -> PA66718 | C74: ='Planilha CP Meli'!E106 -> 271.19 | D74: =IFERROR(VLOOKUP(A74,'Base MLB'!A:B,2,0)," ") -> Premium | E74: =IFERROR(VLOOKUP(A74,'Base MLB'!A:C,3,0)," ") -> 0.165 | F74: =IFERROR(C74/I74," ") -> 0.07999823 | G74: =IFERROR(MAX((ROUNDUP((E74-F74)*100,0)+0.5)/100,4.5%),"") -> 0.095 | H74: =IFERROR((ROUNDUP((E74-F74)*100,0)+0.5)/100,"") -> 0.095 | I74: ='Planilha CP Meli'!G106 -> 3389.95 | J74: =IFERROR(INDEX('Base com preços'!$C:$O,MATCH(B74,'Base com preços'!$A:$A,0),MATCH(G74,'Base com preços'!$C$1:$O$1,0)),IFERROR(INDEX('Boa forma'!$C:$O,MATCH(A74,'Boa forma'!$A:$A,0),MATCH(G74,'Boa forma'!$C$1:$O$1,0)),"")) -> 3288.2554 | K74: =IFERROR(J74-I74," ") -> -101.6946 | L74: =IFERROR(IF(K74<0,"Sim",IF(I74>=J74*0.95,"Sim","Não")),"Não") -> Sim
A75: ='Planilha CP Meli'!B48 -> MLB3580853983 | B75: ='Planilha CP Meli'!C48 -> PA85350 | C75: ='Planilha CP Meli'!E48 -> 153.61 | D75: =IFERROR(VLOOKUP(A75,'Base MLB'!A:B,2,0)," ") -> Clássico | E75: =IFERROR(VLOOKUP(A75,'Base MLB'!A:C,3,0)," ") -> 0.115 | F75: =IFERROR(C75/I75," ") -> 0.079997709 | G75: =IFERROR(MAX((ROUNDUP((E75-F75)*100,0)+0.5)/100,4.5%),"") -> 0.045 | H75: =IFERROR((ROUNDUP((E75-F75)*100,0)+0.5)/100,"") -> 0.045 | I75: ='Planilha CP Meli'!G48 -> 1920.18 | J75: =IFERROR(INDEX('Base com preços'!$C:$O,MATCH(B75,'Base com preços'!$A:$A,0),MATCH(G75,'Base com preços'!$C$1:$O$1,0)),IFERROR(INDEX('Boa forma'!$C:$O,MATCH(A75,'Boa forma'!$A:$A,0),MATCH(G75,'Boa forma'!$C$1:$O$1,0)),"")) -> 1797.829 | K75: =IFERROR(J75-I75," ") -> -122.35101 | L75: =IFERROR(IF(K75<0,"Sim",IF(I75>=J75*0.95,"Sim","Não")),"Não") -> Sim
A76: ='Planilha CP Meli'!B43 -> MLB3570573513 | B76: ='Planilha CP Meli'!C43 -> PA62649 | C76: ='Planilha CP Meli'!E43 -> 59.12 | D76: =IFERROR(VLOOKUP(A76,'Base MLB'!A:B,2,0)," ") -> Premium | E76: =IFERROR(VLOOKUP(A76,'Base MLB'!A:C,3,0)," ") -> 0.165 | F76: =IFERROR(C76/I76," ") -> 0.08 | G76: =IFERROR(MAX((ROUNDUP((E76-F76)*100,0)+0.5)/100,4.5%),"") -> 0.095 | H76: =IFERROR((ROUNDUP((E76-F76)*100,0)+0.5)/100,"") -> 0.095 | I76: ='Planilha CP Meli'!G43 -> 739 | J76: =IFERROR(INDEX('Base com preços'!$C:$O,MATCH(B76,'Base com preços'!$A:$A,0),MATCH(G76,'Base com preços'!$C$1:$O$1,0)),IFERROR(INDEX('Boa forma'!$C:$O,MATCH(A76,'Boa forma'!$A:$A,0),MATCH(G76,'Boa forma'!$C$1:$O$1,0)),"")) -> 872.31429 | K76: =IFERROR(J76-I76," ") -> 133.31429 | L76: =IFERROR(IF(K76<0,"Sim",IF(I76>=J76*0.95,"Sim","Não")),"Não") -> Não
A77: ='Planilha CP Meli'!B41 -> MLB3569859257 | B77: ='Planilha CP Meli'!C41 -> PA71948 | C77: ='Planilha CP Meli'!E41 -> 111.42 | D77: =IFERROR(VLOOKUP(A77,'Base MLB'!A:B,2,0)," ") -> Clássico | E77: =IFERROR(VLOOKUP(A77,'Base MLB'!A:C,3,0)," ") -> 0.115 | F77: =IFERROR(C77/I77," ") -> 0.055164424 | G77: =IFERROR(MAX((ROUNDUP((E77-F77)*100,0)+0.5)/100,4.5%),"") -> 0.065 | H77: =IFERROR((ROUNDUP((E77-F77)*100,0)+0.5)/100,"") -> 0.065 | I77: ='Planilha CP Meli'!G41 -> 2019.78 | J77: =IFERROR(INDEX('Base com preços'!$C:$O,MATCH(B77,'Base com preços'!$A:$A,0),MATCH(G77,'Base com preços'!$C$1:$O$1,0)),IFERROR(INDEX('Boa forma'!$C:$O,MATCH(A77,'Boa forma'!$A:$A,0),MATCH(G77,'Boa forma'!$C$1:$O$1,0)),"")) -> 1788.1001 | K77: =IFERROR(J77-I77," ") -> -231.6799 | L77: =IFERROR(IF(K77<0,"Sim",IF(I77>=J77*0.95,"Sim","Não")),"Não") -> Sim
A78: ='Planilha CP Meli'!B29 -> MLB3544962893 | B78: ='Planilha CP Meli'!C29 -> PA65756 | C78: ='Planilha CP Meli'!E29 -> 108.88 | D78: =IFERROR(VLOOKUP(A78,'Base MLB'!A:B,2,0)," ") -> Premium | E78: =IFERROR(VLOOKUP(A78,'Base MLB'!A:C,3,0)," ") -> 0.165 | F78: =IFERROR(C78/I78," ") -> 0.079995298 | G78: =IFERROR(MAX((ROUNDUP((E78-F78)*100,0)+0.5)/100,4.5%),"") -> 0.095 | H78: =IFERROR((ROUNDUP((E78-F78)*100,0)+0.5)/100,"") -> 0.095 | I78: ='Planilha CP Meli'!G29 -> 1361.08 | J78: =IFERROR(INDEX('Base com preços'!$C:$O,MATCH(B78,'Base com preços'!$A:$A,0),MATCH(G78,'Base com preços'!$C$1:$O$1,0)),IFERROR(INDEX('Boa forma'!$C:$O,MATCH(A78,'Boa forma'!$A:$A,0),MATCH(G78,'Boa forma'!$C$1:$O$1,0)),"")) -> 1320.2501 | K78: =IFERROR(J78-I78," ") -> -40.829904 | L78: =IFERROR(IF(K78<0,"Sim",IF(I78>=J78*0.95,"Sim","Não")),"Não") -> Sim
A79: ='Planilha CP Meli'!B51 -> MLB3593456033 | B79: ='Planilha CP Meli'!C51 -> PA69948 | C79: ='Planilha CP Meli'!E51 -> 114.72 | D79: =IFERROR(VLOOKUP(A79,'Base MLB'!A:B,2,0)," ") -> Clássico | E79: =IFERROR(VLOOKUP(A79,'Base MLB'!A:C,3,0)," ") -> 0.115 | F79: =IFERROR(C79/I79," ") -> 0.08 | G79: =IFERROR(MAX((ROUNDUP((E79-F79)*100,0)+0.5)/100,4.5%),"") -> 0.045 | H79: =IFERROR((ROUNDUP((E79-F79)*100,0)+0.5)/100,"") -> 0.045 | I79: ='Planilha CP Meli'!G51 -> 1434 | J79: =IFERROR(INDEX('Base com preços'!$C:$O,MATCH(B79,'Base com preços'!$A:$A,0),MATCH(G79,'Base com preços'!$C$1:$O$1,0)),IFERROR(INDEX('Boa forma'!$C:$O,MATCH(A79,'Boa forma'!$A:$A,0),MATCH(G79,'Boa forma'!$C$1:$O$1,0)),"")) -> 1235.6027 | K79: =IFERROR(J79-I79," ") -> -198.3973 | L79: =IFERROR(IF(K79<0,"Sim",IF(I79>=J79*0.95,"Sim","Não")),"Não") -> Sim
A80: ='Planilha CP Meli'!B62 -> MLB3595908497 | B80: ='Planilha CP Meli'!C62 -> PA69848 | C80: ='Planilha CP Meli'!E62 -> 92.5 | D80: =IFERROR(VLOOKUP(A80,'Base MLB'!A:B,2,0)," ") -> Clássico | E80: =IFERROR(VLOOKUP(A80,'Base MLB'!A:C,3,0)," ") -> 0.115 | F80: =IFERROR(C80/I80," ") -> 0.061258278 | G80: =IFERROR(MAX((ROUNDUP((E80-F80)*100,0)+0.5)/100,4.5%),"") -> 0.065 | H80: =IFERROR((ROUNDUP((E80-F80)*100,0)+0.5)/100,"") -> 0.065 | I80: ='Planilha CP Meli'!G62 -> 1510 | J80: =IFERROR(INDEX('Base com preços'!$C:$O,MATCH(B80,'Base com preços'!$A:$A,0),MATCH(G80,'Base com preços'!$C$1:$O$1,0)),IFERROR(INDEX('Boa forma'!$C:$O,MATCH(A80,'Boa forma'!$A:$A,0),MATCH(G80,'Boa forma'!$C$1:$O$1,0)),"")) -> 1342.2153 | K80: =IFERROR(J80-I80," ") -> -167.78471 | L80: =IFERROR(IF(K80<0,"Sim",IF(I80>=J80*0.95,"Sim","Não")),"Não") -> Sim
A81: ='Planilha CP Meli'!B47 -> MLB3580216353 | B81: ='Planilha CP Meli'!C47 -> PA85370 | C81: ='Planilha CP Meli'!E47 -> 124.56 | D81: =IFERROR(VLOOKUP(A81,'Base MLB'!A:B,2,0)," ") -> Clássico | E81: =IFERROR(VLOOKUP(A81,'Base MLB'!A:C,3,0)," ") -> 0.115 | F81: =IFERROR(C81/I81," ") -> 0.068695849 | G81: =IFERROR(MAX((ROUNDUP((E81-F81)*100,0)+0.5)/100,4.5%),"") -> 0.055 | H81: =IFERROR((ROUNDUP((E81-F81)*100,0)+0.5)/100,"") -> 0.055 | I81: ='Planilha CP Meli'!G47 -> 1813.21 | J81: =IFERROR(INDEX('Base com preços'!$C:$O,MATCH(B81,'Base com preços'!$A:$A,0),MATCH(G81,'Base com preços'!$C$1:$O$1,0)),IFERROR(INDEX('Boa forma'!$C:$O,MATCH(A81,'Boa forma'!$A:$A,0),MATCH(G81,'Boa forma'!$C$1:$O$1,0)),"")) -> 1557.0716 | K81: =IFERROR(J81-I81," ") -> -256.13839 | L81: =IFERROR(IF(K81<0,"Sim",IF(I81>=J81*0.95,"Sim","Não")),"Não") -> Sim
A82: ='Planilha CP Meli'!B15 -> MLB3482157617 | B82: ='Planilha CP Meli'!C15 -> PA66731 | C82: ='Planilha CP Meli'!E15 -> 170.6 | D82: =IFERROR(VLOOKUP(A82,'Base MLB'!A:B,2,0)," ") -> Clássico | E82: =IFERROR(VLOOKUP(A82,'Base MLB'!A:C,3,0)," ") -> 0.115 | F82: =IFERROR(C82/I82," ") -> 0.0568697 | G82: =IFERROR(MAX((ROUNDUP((E82-F82)*100,0)+0.5)/100,4.5%),"") -> 0.065 | H82: =IFERROR((ROUNDUP((E82-F82)*100,0)+0.5)/100,"") -> 0.065 | I82: ='Planilha CP Meli'!G15 -> 2999.84 | J82: =IFERROR(INDEX('Base com preços'!$C:$O,MATCH(B82,'Base com preços'!$A:$A,0),MATCH(G82,'Base com preços'!$C$1:$O$1,0)),IFERROR(INDEX('Boa forma'!$C:$O,MATCH(A82,'Boa forma'!$A:$A,0),MATCH(G82,'Boa forma'!$C$1:$O$1,0)),"")) -> 2655.7397 | K82: =IFERROR(J82-I82," ") -> -344.10027 | L82: =IFERROR(IF(K82<0,"Sim",IF(I82>=J82*0.95,"Sim","Não")),"Não") -> Sim
A83: ='Planilha CP Meli'!B46 -> MLB3576596273 | B83: ='Planilha CP Meli'!C46 -> PA85370 | C83: ='Planilha CP Meli'!E46 -> 145.05 | D83: =IFERROR(VLOOKUP(A83,'Base MLB'!A:B,2,0)," ") -> Premium | E83: =IFERROR(VLOOKUP(A83,'Base MLB'!A:C,3,0)," ") -> 0.165 | F83: =IFERROR(C83/I83," ") -> 0.079995809 | G83: =IFERROR(MAX((ROUNDUP((E83-F83)*100,0)+0.5)/100,4.5%),"") -> 0.095 | H83: =IFERROR((ROUNDUP((E83-F83)*100,0)+0.5)/100,"") -> 0.095 | I83: ='Planilha CP Meli'!G46 -> 1813.22 | J83: =IFERROR(INDEX('Base com preços'!$C:$O,MATCH(B83,'Base com preços'!$A:$A,0),MATCH(G83,'Base com preços'!$C$1:$O$1,0)),IFERROR(INDEX('Boa forma'!$C:$O,MATCH(A83,'Boa forma'!$A:$A,0),MATCH(G83,'Boa forma'!$C$1:$O$1,0)),"")) -> 1758.821 | K83: =IFERROR(J83-I83," ") -> -54.398971 | L83: =IFERROR(IF(K83<0,"Sim",IF(I83>=J83*0.95,"Sim","Não")),"Não") -> Sim
A84: ='Planilha CP Meli'!B65 -> MLB3595933755 | B84: ='Planilha CP Meli'!C65 -> PA56216 | C84: ='Planilha CP Meli'!E65 -> 157.85 | D84: =IFERROR(VLOOKUP(A84,'Base MLB'!A:B,2,0)," ") -> Clássico | E84: =IFERROR(VLOOKUP(A84,'Base MLB'!A:C,3,0)," ") -> 0.115 | F84: =IFERROR(C84/I84," ") -> 0.059001626 | G84: =IFERROR(MAX((ROUNDUP((E84-F84)*100,0)+0.5)/100,4.5%),"") -> 0.065 | H84: =IFERROR((ROUNDUP((E84-F84)*100,0)+0.5)/100,"") -> 0.065 | I84: ='Planilha CP Meli'!G65 -> 2675.35 | J84: =IFERROR(INDEX('Base com preços'!$C:$O,MATCH(B84,'Base com preços'!$A:$A,0),MATCH(G84,'Base com preços'!$C$1:$O$1,0)),IFERROR(INDEX('Boa forma'!$C:$O,MATCH(A84,'Boa forma'!$A:$A,0),MATCH(G84,'Boa forma'!$C$1:$O$1,0)),"")) -> 2368.4697 | K84: =IFERROR(J84-I84," ") -> -306.8803 | L84: =IFERROR(IF(K84<0,"Sim",IF(I84>=J84*0.95,"Sim","Não")),"Não") -> Sim
A85: ='Planilha CP Meli'!B119 -> MLB4218390214 | B85: ='Planilha CP Meli'!C119 -> PA66794 | C85: ='Planilha CP Meli'!E119 -> 193.97 | D85: =IFERROR(VLOOKUP(A85,'Base MLB'!A:B,2,0)," ") -> Clássico | E85: =IFERROR(VLOOKUP(A85,'Base MLB'!A:C,3,0)," ") -> 0.115 | F85: =IFERROR(C85/I85," ") -> 0.052877643 | G85: =IFERROR(MAX((ROUNDUP((E85-F85)*100,0)+0.5)/100,4.5%),"") -> 0.075 | H85: =IFERROR((ROUNDUP((E85-F85)*100,0)+0.5)/100,"") -> 0.075 | I85: ='Planilha CP Meli'!G119 -> 3668.28 | J85: =IFERROR(INDEX('Base com preços'!$C:$O,MATCH(B85,'Base com preços'!$A:$A,0),MATCH(G85,'Base com preços'!$C$1:$O$1,0)),IFERROR(INDEX('Boa forma'!$C:$O,MATCH(A85,'Boa forma'!$A:$A,0),MATCH(G85,'Boa forma'!$C$1:$O$1,0)),"")) -> 3347.9401 | K85: =IFERROR(J85-I85," ") -> -320.33986 | L85: =IFERROR(IF(K85<0,"Sim",IF(I85>=J85*0.95,"Sim","Não")),"Não") -> Sim
A86: ='Planilha CP Meli'!B91 -> MLB3982045865 | B86: ='Planilha CP Meli'!C91 -> PA52310 | C86: ='Planilha CP Meli'!E91 -> 105.54 | D86: =IFERROR(VLOOKUP(A86,'Base MLB'!A:B,2,0)," ") -> Clássico | E86: =IFERROR(VLOOKUP(A86,'Base MLB'!A:C,3,0)," ") -> 0.115 | F86: =IFERROR(C86/I86," ") -> 0.066068209 | G86: =IFERROR(MAX((ROUNDUP((E86-F86)*100,0)+0.5)/100,4.5%),"") -> 0.055 | H86: =IFERROR((ROUNDUP((E86-F86)*100,0)+0.5)/100,"") -> 0.055 | I86: ='Planilha CP Meli'!G91 -> 1597.44 | J86: =IFERROR(INDEX('Base com preços'!$C:$O,MATCH(B86,'Base com preços'!$A:$A,0),MATCH(G86,'Base com preços'!$C$1:$O$1,0)),IFERROR(INDEX('Boa forma'!$C:$O,MATCH(A86,'Boa forma'!$A:$A,0),MATCH(G86,'Boa forma'!$C$1:$O$1,0)),"")) -> 1371.7856 | K86: =IFERROR(J86-I86," ") -> -225.65436 | L86: =IFERROR(IF(K86<0,"Sim",IF(I86>=J86*0.95,"Sim","Não")),"Não") -> Sim
A87: ='Planilha CP Meli'!B44 -> MLB3570610029 | B87: ='Planilha CP Meli'!C44 -> PA67504 | C87: ='Planilha CP Meli'!E44 -> 107.33 | D87: =IFERROR(VLOOKUP(A87,'Base MLB'!A:B,2,0)," ") -> Clássico | E87: =IFERROR(VLOOKUP(A87,'Base MLB'!A:C,3,0)," ") -> 0.115 | F87: =IFERROR(C87/I87," ") -> 0.05611674 | G87: =IFERROR(MAX((ROUNDUP((E87-F87)*100,0)+0.5)/100,4.5%),"") -> 0.065 | H87: =IFERROR((ROUNDUP((E87-F87)*100,0)+0.5)/100,"") -> 0.065 | I87: ='Planilha CP Meli'!G44 -> 1912.62 | J87: =IFERROR(INDEX('Base com preços'!$C:$O,MATCH(B87,'Base com preços'!$A:$A,0),MATCH(G87,'Base com preços'!$C$1:$O$1,0)),IFERROR(INDEX('Boa forma'!$C:$O,MATCH(A87,'Boa forma'!$A:$A,0),MATCH(G87,'Boa forma'!$C$1:$O$1,0)),"")) -> 1693.2283 | K87: =IFERROR(J87-I87," ") -> -219.39174 | L87: =IFERROR(IF(K87<0,"Sim",IF(I87>=J87*0.95,"Sim","Não")),"Não") -> Sim
A88: ='Planilha CP Meli'!B121 -> MLB4240665500 | B88: ='Planilha CP Meli'!C121 -> PA66746 | C88: ='Planilha CP Meli'!E121 -> 149.04 | D88: =IFERROR(VLOOKUP(A88,'Base MLB'!A:B,2,0)," ") -> Clássico | E88: =IFERROR(VLOOKUP(A88,'Base MLB'!A:C,3,0)," ") -> 0.115 | F88: =IFERROR(C88/I88," ") -> 0.045600015 | G88: =IFERROR(MAX((ROUNDUP((E88-F88)*100,0)+0.5)/100,4.5%),"") -> 0.075 | H88: =IFERROR((ROUNDUP((E88-F88)*100,0)+0.5)/100,"") -> 0.075 | I88: ='Planilha CP Meli'!G121 -> 3268.42 | J88: =IFERROR(INDEX('Base com preços'!$C:$O,MATCH(B88,'Base com preços'!$A:$A,0),MATCH(G88,'Base com preços'!$C$1:$O$1,0)),IFERROR(INDEX('Boa forma'!$C:$O,MATCH(A88,'Boa forma'!$A:$A,0),MATCH(G88,'Boa forma'!$C$1:$O$1,0)),"")) -> 2983.0095 | K88: =IFERROR(J88-I88," ") -> -285.41054 | L88: =IFERROR(IF(K88<0,"Sim",IF(I88>=J88*0.95,"Sim","Não")),"Não") -> Sim
A89: ='Planilha CP Meli'!B12 -> MLB3474545921 | B89: ='Planilha CP Meli'!C12 -> PA66725 | C89: ='Planilha CP Meli'!E12 -> 186.5 | D89: =IFERROR(VLOOKUP(A89,'Base MLB'!A:B,2,0)," ") -> Premium | E89: =IFERROR(VLOOKUP(A89,'Base MLB'!A:C,3,0)," ") -> 0.165 | F89: =IFERROR(C89/I89," ") -> 0.078299166 | G89: =IFERROR(MAX((ROUNDUP((E89-F89)*100,0)+0.5)/100,4.5%),"") -> 0.095 | H89: =IFERROR((ROUNDUP((E89-F89)*100,0)+0.5)/100,"") -> 0.095 | I89: ='Planilha CP Meli'!G12 -> 2381.89 | J89: =IFERROR(INDEX('Base com preços'!$C:$O,MATCH(B89,'Base com preços'!$A:$A,0),MATCH(G89,'Base com preços'!$C$1:$O$1,0)),IFERROR(INDEX('Boa forma'!$C:$O,MATCH(A89,'Boa forma'!$A:$A,0),MATCH(G89,'Boa forma'!$C$1:$O$1,0)),"")) -> 2310.436 | K89: =IFERROR(J89-I89," ") -> -71.453967 | L89: =IFERROR(IF(K89<0,"Sim",IF(I89>=J89*0.95,"Sim","Não")),"Não") -> Sim
A90: ='Planilha CP Meli'!B196 -> MLB5184890542 | B90: ='Planilha CP Meli'!C196 -> PA51522 | C90: ='Planilha CP Meli'!E196 -> 38.01 | D90: =IFERROR(VLOOKUP(A90,'Base MLB'!A:B,2,0)," ") -> Premium | E90: =IFERROR(VLOOKUP(A90,'Base MLB'!A:C,3,0)," ") -> 0.165 | F90: =IFERROR(C90/I90," ") -> 0.07 | G90: =IFERROR(MAX((ROUNDUP((E90-F90)*100,0)+0.5)/100,4.5%),"") -> 0.105 | H90: =IFERROR((ROUNDUP((E90-F90)*100,0)+0.5)/100,"") -> 0.105 | I90: ='Planilha CP Meli'!G196 -> 543 | J90: =IFERROR(INDEX('Base com preços'!$C:$O,MATCH(B90,'Base com preços'!$A:$A,0),MATCH(G90,'Base com preços'!$C$1:$O$1,0)),IFERROR(INDEX('Boa forma'!$C:$O,MATCH(A90,'Boa forma'!$A:$A,0),MATCH(G90,'Boa forma'!$C$1:$O$1,0)),"")) -> 794.27954 | K90: =IFERROR(J90-I90," ") -> 251.27954 | L90: =IFERROR(IF(K90<0,"Sim",IF(I90>=J90*0.95,"Sim","Não")),"Não") -> Não
A91: ='Planilha CP Meli'!B90 -> MLB3980137463 | B91: ='Planilha CP Meli'!C90 -> PA65751 | C91: ='Planilha CP Meli'!E90 -> 35.42 | D91: =IFERROR(VLOOKUP(A91,'Base MLB'!A:B,2,0)," ") -> Clássico | E91: =IFERROR(VLOOKUP(A91,'Base MLB'!A:C,3,0)," ") -> 0.115 | F91: =IFERROR(C91/I91," ") -> 0.07 | G91: =IFERROR(MAX((ROUNDUP((E91-F91)*100,0)+0.5)/100,4.5%),"") -> 0.055 | H91: =IFERROR((ROUNDUP((E91-F91)*100,0)+0.5)/100,"") -> 0.055 | I91: ='Planilha CP Meli'!G90 -> 506 | J91: =IFERROR(INDEX('Base com preços'!$C:$O,MATCH(B91,'Base com preços'!$A:$A,0),MATCH(G91,'Base com preços'!$C$1:$O$1,0)),IFERROR(INDEX('Boa forma'!$C:$O,MATCH(A91,'Boa forma'!$A:$A,0),MATCH(G91,'Boa forma'!$C$1:$O$1,0)),"")) -> 580.24307 | K91: =IFERROR(J91-I91," ") -> 74.243068 | L91: =IFERROR(IF(K91<0,"Sim",IF(I91>=J91*0.95,"Sim","Não")),"Não") -> Não
A92: ='Planilha CP Meli'!B94 -> MLB4019821965 | B92: ='Planilha CP Meli'!C94 -> PA66760 | C92: ='Planilha CP Meli'!E94 -> 79.03 | D92: =IFERROR(VLOOKUP(A92,'Base MLB'!A:B,2,0)," ") -> Clássico | E92: =IFERROR(VLOOKUP(A92,'Base MLB'!A:C,3,0)," ") -> 0.115 | F92: =IFERROR(C92/I92," ") -> 0.033708105 | G92: =IFERROR(MAX((ROUNDUP((E92-F92)*100,0)+0.5)/100,4.5%),"") -> 0.095 | H92: =IFERROR((ROUNDUP((E92-F92)*100,0)+0.5)/100,"") -> 0.095 | I92: ='Planilha CP Meli'!G94 -> 2344.54 | J92: =IFERROR(INDEX('Base com preços'!$C:$O,MATCH(B92,'Base com preços'!$A:$A,0),MATCH(G92,'Base com preços'!$C$1:$O$1,0)),IFERROR(INDEX('Boa forma'!$C:$O,MATCH(A92,'Boa forma'!$A:$A,0),MATCH(G92,'Boa forma'!$C$1:$O$1,0)),"")) -> 2274.2112 | K92: =IFERROR(J92-I92," ") -> -70.328766 | L92: =IFERROR(IF(K92<0,"Sim",IF(I92>=J92*0.95,"Sim","Não")),"Não") -> Sim
A93: ='Planilha CP Meli'!B17 -> MLB3482209147 | B93: ='Planilha CP Meli'!C17 -> PA66749 | C93: ='Planilha CP Meli'!E17 -> 197.53 | D93: =IFERROR(VLOOKUP(A93,'Base MLB'!A:B,2,0)," ") -> Clássico | E93: =IFERROR(VLOOKUP(A93,'Base MLB'!A:C,3,0)," ") -> 0.115 | F93: =IFERROR(C93/I93," ") -> 0.04192481 | G93: =IFERROR(MAX((ROUNDUP((E93-F93)*100,0)+0.5)/100,4.5%),"") -> 0.085 | H93: =IFERROR((ROUNDUP((E93-F93)*100,0)+0.5)/100,"") -> 0.085 | I93: ='Planilha CP Meli'!G17 -> 4711.53 | J93: =IFERROR(INDEX('Base com preços'!$C:$O,MATCH(B93,'Base com preços'!$A:$A,0),MATCH(G93,'Base com preços'!$C$1:$O$1,0)),IFERROR(INDEX('Boa forma'!$C:$O,MATCH(A93,'Boa forma'!$A:$A,0),MATCH(G93,'Boa forma'!$C$1:$O$1,0)),"")) -> 4433.085 | K93: =IFERROR(J93-I93," ") -> -278.44501 | L93: =IFERROR(IF(K93<0,"Sim",IF(I93>=J93*0.95,"Sim","Não")),"Não") -> Sim
A94: ='Planilha CP Meli'!B53 -> MLB3595845505 | B94: ='Planilha CP Meli'!C53 -> PA62653 | C94: ='Planilha CP Meli'!E53 -> 112.19 | D94: =IFERROR(VLOOKUP(A94,'Base MLB'!A:B,2,0)," ") -> Clássico | E94: =IFERROR(VLOOKUP(A94,'Base MLB'!A:C,3,0)," ") -> 0.115 | F94: =IFERROR(C94/I94," ") -> 0.070515399 | G94: =IFERROR(MAX((ROUNDUP((E94-F94)*100,0)+0.5)/100,4.5%),"") -> 0.055 | H94: =IFERROR((ROUNDUP((E94-F94)*100,0)+0.5)/100,"") -> 0.055 | I94: ='Planilha CP Meli'!G53 -> 1591 | J94: =IFERROR(INDEX('Base com preços'!$C:$O,MATCH(B94,'Base com preços'!$A:$A,0),MATCH(G94,'Base com preços'!$C$1:$O$1,0)),IFERROR(INDEX('Boa forma'!$C:$O,MATCH(A94,'Boa forma'!$A:$A,0),MATCH(G94,'Boa forma'!$C$1:$O$1,0)),"")) -> 1413.6262 | K94: =IFERROR(J94-I94," ") -> -177.37381 | L94: =IFERROR(IF(K94<0,"Sim",IF(I94>=J94*0.95,"Sim","Não")),"Não") -> Sim
A95: ='Planilha CP Meli'!B50 -> MLB3593416973 | B95: ='Planilha CP Meli'!C50 -> PA58273 | C95: ='Planilha CP Meli'!E50 -> 134.97 | D95: =IFERROR(VLOOKUP(A95,'Base MLB'!A:B,2,0)," ") -> Clássico | E95: =IFERROR(VLOOKUP(A95,'Base MLB'!A:C,3,0)," ") -> 0.115 | F95: =IFERROR(C95/I95," ") -> 0.079996444 | G95: =IFERROR(MAX((ROUNDUP((E95-F95)*100,0)+0.5)/100,4.5%),"") -> 0.045 | H95: =IFERROR((ROUNDUP((E95-F95)*100,0)+0.5)/100,"") -> 0.045 | I95: ='Planilha CP Meli'!G50 -> 1687.2 | J95: =IFERROR(INDEX('Base com preços'!$C:$O,MATCH(B95,'Base com preços'!$A:$A,0),MATCH(G95,'Base com preços'!$C$1:$O$1,0)),IFERROR(INDEX('Boa forma'!$C:$O,MATCH(A95,'Boa forma'!$A:$A,0),MATCH(G95,'Boa forma'!$C$1:$O$1,0)),"")) -> 1405.3926 | K95: =IFERROR(J95-I95," ") -> -281.80735 | L95: =IFERROR(IF(K95<0,"Sim",IF(I95>=J95*0.95,"Sim","Não")),"Não") -> Sim
A96: ='Planilha CP Meli'!B191 -> MLB5184813968 | B96: ='Planilha CP Meli'!C191 -> PA52107 | C96: ='Planilha CP Meli'!E191 -> 160.17 | D96: =IFERROR(VLOOKUP(A96,'Base MLB'!A:B,2,0)," ") -> Premium | E96: =IFERROR(VLOOKUP(A96,'Base MLB'!A:C,3,0)," ") -> 0.165 | F96: =IFERROR(C96/I96," ") -> 0.072965401 | G96: =IFERROR(MAX((ROUNDUP((E96-F96)*100,0)+0.5)/100,4.5%),"") -> 0.105 | H96: =IFERROR((ROUNDUP((E96-F96)*100,0)+0.5)/100,"") -> 0.105 | I96: ='Planilha CP Meli'!G191 -> 2195.15 | J96: =IFERROR(INDEX('Base com preços'!$C:$O,MATCH(B96,'Base com preços'!$A:$A,0),MATCH(G96,'Base com preços'!$C$1:$O$1,0)),IFERROR(INDEX('Boa forma'!$C:$O,MATCH(A96,'Boa forma'!$A:$A,0),MATCH(G96,'Boa forma'!$C$1:$O$1,0)),"")) -> 2195.1527 | K96: =IFERROR(J96-I96," ") -> 0.0027185556 | L96: =IFERROR(IF(K96<0,"Sim",IF(I96>=J96*0.95,"Sim","Não")),"Não") -> Sim
A97: ='Planilha CP Meli'!B108 -> MLB4130288018 | B97: ='Planilha CP Meli'!C108 -> PA85354 | C97: ='Planilha CP Meli'!E108 -> 229.64 | D97: =IFERROR(VLOOKUP(A97,'Base MLB'!A:B,2,0)," ") -> Clássico | E97: =IFERROR(VLOOKUP(A97,'Base MLB'!A:C,3,0)," ") -> 0.115 | F97: =IFERROR(C97/I97," ") -> 0.068682313 | G97: =IFERROR(MAX((ROUNDUP((E97-F97)*100,0)+0.5)/100,4.5%),"") -> 0.055 | H97: =IFERROR((ROUNDUP((E97-F97)*100,0)+0.5)/100,"") -> 0.055 | I97: ='Planilha CP Meli'!G108 -> 3343.51 | J97: =IFERROR(INDEX('Base com preços'!$C:$O,MATCH(B97,'Base com preços'!$A:$A,0),MATCH(G97,'Base com preços'!$C$1:$O$1,0)),IFERROR(INDEX('Boa forma'!$C:$O,MATCH(A97,'Boa forma'!$A:$A,0),MATCH(G97,'Boa forma'!$C$1:$O$1,0)),"")) -> 2871.1911 | K97: =IFERROR(J97-I97," ") -> -472.31888 | L97: =IFERROR(IF(K97<0,"Sim",IF(I97>=J97*0.95,"Sim","Não")),"Não") -> Sim
A98: ='Planilha CP Meli'!B58 -> MLB3595895575 | B98: ='Planilha CP Meli'!C58 -> PA67505 | C98: ='Planilha CP Meli'!E58 -> 199.79 | D98: =IFERROR(VLOOKUP(A98,'Base MLB'!A:B,2,0)," ") -> Premium | E98: =IFERROR(VLOOKUP(A98,'Base MLB'!A:C,3,0)," ") -> 0.165 | F98: =IFERROR(C98/I98," ") -> 0.076460008 | G98: =IFERROR(MAX((ROUNDUP((E98-F98)*100,0)+0.5)/100,4.5%),"") -> 0.095 | H98: =IFERROR((ROUNDUP((E98-F98)*100,0)+0.5)/100,"") -> 0.095 | I98: ='Planilha CP Meli'!G58 -> 2613 | J98: =IFERROR(INDEX('Base com preços'!$C:$O,MATCH(B98,'Base com preços'!$A:$A,0),MATCH(G98,'Base com preços'!$C$1:$O$1,0)),IFERROR(INDEX('Boa forma'!$C:$O,MATCH(A98,'Boa forma'!$A:$A,0),MATCH(G98,'Boa forma'!$C$1:$O$1,0)),"")) -> 2294.1381 | K98: =IFERROR(J98-I98," ") -> -318.86194 | L98: =IFERROR(IF(K98<0,"Sim",IF(I98>=J98*0.95,"Sim","Não")),"Não") -> Sim
A99: ='Planilha CP Meli'!B76 -> MLB3732100219 | B99: ='Planilha CP Meli'!C76 -> PA71948 | C99: ='Planilha CP Meli'!E76 -> 179.6 | D99: =IFERROR(VLOOKUP(A99,'Base MLB'!A:B,2,0)," ") -> Premium | E99: =IFERROR(VLOOKUP(A99,'Base MLB'!A:C,3,0)," ") -> 0.165 | F99: =IFERROR(C99/I99," ") -> 0.08 | G99: =IFERROR(MAX((ROUNDUP((E99-F99)*100,0)+0.5)/100,4.5%),"") -> 0.095 | H99: =IFERROR((ROUNDUP((E99-F99)*100,0)+0.5)/100,"") -> 0.095 | I99: ='Planilha CP Meli'!G76 -> 2245 | J99: =IFERROR(INDEX('Base com preços'!$C:$O,MATCH(B99,'Base com preços'!$A:$A,0),MATCH(G99,'Base com preços'!$C$1:$O$1,0)),IFERROR(INDEX('Boa forma'!$C:$O,MATCH(A99,'Boa forma'!$A:$A,0),MATCH(G99,'Boa forma'!$C$1:$O$1,0)),"")) -> 1959.1903 | K99: =IFERROR(J99-I99," ") -> -285.80968 | L99: =IFERROR(IF(K99<0,"Sim",IF(I99>=J99*0.95,"Sim","Não")),"Não") -> Sim
A100: ='Planilha CP Meli'!B57 -> MLB3595895555 | B100: ='Planilha CP Meli'!C57 -> PA62652 | C100: ='Planilha CP Meli'!E57 -> 101.28 | D100: =IFERROR(VLOOKUP(A100,'Base MLB'!A:B,2,0)," ") -> Clássico | E100: =IFERROR(VLOOKUP(A100,'Base MLB'!A:C,3,0)," ") -> 0.115 | F100: =IFERROR(C100/I100," ") -> 0.08 | G100: =IFERROR(MAX((ROUNDUP((E100-F100)*100,0)+0.5)/100,4.5%),"") -> 0.045 | H100: =IFERROR((ROUNDUP((E100-F100)*100,0)+0.5)/100,"") -> 0.045 | I100: ='Planilha CP Meli'!G57 -> 1266 | J100: =IFERROR(INDEX('Base com preços'!$C:$O,MATCH(B100,'Base com preços'!$A:$A,0),MATCH(G100,'Base com preços'!$C$1:$O$1,0)),IFERROR(INDEX('Boa forma'!$C:$O,MATCH(A100,'Boa forma'!$A:$A,0),MATCH(G100,'Boa forma'!$C$1:$O$1,0)),"")) -> 1132.9218 | K100: =IFERROR(J100-I100," ") -> -133.07821 | L100: =IFERROR(IF(K100<0,"Sim",IF(I100>=J100*0.95,"Sim","Não")),"Não") -> Sim
...

Sheet Base MLB
A1: Anúncio MLB | B1: Tipo de Anúncio | C1: Comissão padrão
A2: MLB3563984623 | B2: Clássico | C2: 0.115
A3: MLB4039588653 | B3: Clássico | C3: 0.115
A4: MLB5337068004 | B4: Clássico | C4: 0.115
A5: MLB4282219223 | B5: Clássico | C5: 0.115
A6: MLB3967091117 | B6: Clássico | C6: 0.115
A7: MLB5298314016 | B7: Clássico | C7: 0.115
A8: MLB4039492363 | B8: Clássico | C8: 0.115
A9: MLB4373183516 | B9: Clássico | C9: 0.115
A10: MLB3564008305 | B10: Clássico | C10: 0.115
A11: MLB4039492345 | B11: Clássico | C11: 0.115
A12: MLB5336288854 | B12: Clássico | C12: 0.115
A13: MLB4512899968 | B13: Clássico | C13: 0.115
... A1323: MLB7226100646 | B1323: Premium | C1323: 0.165

Sheet Planilha CP Meli
A1: TITLE | B1: ITEM_ID | C1: SKU | D1: ORIGINAL_PRICE | E1: SALE_FEE | F1: DISCOUNT_PERCENTAGE | G1: FINAL_PRICE | H1: STATUS | I1: ACTION | J1: ERRORS | K1: CANDIDATE_ID
A2: Título do anúncio | B2: Número do anúncio | C2: SKU | D2: Preço original | E2: Redução nas suas tarifas de venda | F2: Desconto total | G2: Preço final | H2: Status da promoção | I2: O que você quer fazer com este anúncio? | J2: Observações e erros Não altere este campo
A4: Não altere esta coluna | B4: Não altere esta coluna | C4: Não altere esta coluna | D4: Não altere esta coluna | E4: Não altere esta coluna | F4: Não altere esta coluna | G4: Não altere esta coluna | H4: Não altere este campo
A6: Conjunto Box Solteiro Mola Ensacada Probel Excede Premium Branco | B6: MLB3473649173 | C6: PA85366 | D6: 2995 | E6: 100.98 | F6: 34 | G6: 1985.2 | H6: Elegível | I6: Participar | K6: CANDIDATE-MLB3473649173-77071962499
A7: Colchão Solteiro Mola Ensacada Probel Excede Premium | B7: MLB3473661733 | C7: PA85347 | D7: 2732.9 | E7: 87.92 | F7: 60 | G7: 1099 | H7: Elegível | I7: Participar | K7: CANDIDATE-MLB3473661733-77073956323
A8: Conjunto Box Queen Mola Ensacada Probel Excede Premium Cor Branco | B8: MLB3473786083 | C8: PA85368 | D8: 5542 | E8: 238.24 | F8: 46 | G8: 2978 | H8: Elegível | I8: Participar | K8: CANDIDATE-MLB3473786083-77072014305
A9: Colchão Queen Mola Ensacada Probel Bari | B9: MLB3474507063 | C9: PA66716 | D9: 5050.9 | E9: 197.84 | F9: 51 | G9: 2473 | H9: Elegível | I9: Participar | K9: CANDIDATE-MLB3474507063-77071962584
A10: Colchão Solteiro Mola Ensacada Probel Turim | B10: MLB3474545447 | C10: PA85357 | D10: 2746.9 | E10: 107.34 | F10: 51 | G10: 1341.8 | H10: Elegível | I10: Participar | K10: CANDIDATE-MLB3474545447-77073633168
A11: Colchão Casal Mola Probel Siena | B11: MLB3474545857 | C11: PA66724 | D11: 3722.9 | E11: 162.02 | F11: 46 | G11: 2025.37 | H11: Elegível | I11: Participar | K11: CANDIDATE-MLB3474545857-77071234818
A12: Colchão Queen Mola Probel Siena | B12: MLB3474545921 | C12: PA66725 | D12: 4246.9 | E12: 186.5 | F12: 44 | G12: 2381.89 | H12: Elegível | I12: Participar | K12: CANDIDATE-MLB3474545921-77071237813
A13: Conjunto Box Casal Mola Ensacada Probel Turim Branco | B13: MLB3474583509 | C13: PA85371 | D13: 5053.9 | E13: 211.27 | F13: 48 | G13: 2640.91 | H13: Elegível | I13: Participar | K13: CANDIDATE-MLB3474583509-77073912242
A14: Colchão Queen Mola Ensacada Probel Turim | B14: MLB3474584357 | C14: PA85361 | D14: 4806.9 | E14: 202.96 | F14: 42 | G14: 2777.21 | H14: Elegível | I14: Participar | K14: CANDIDATE-MLB3474584357-77071258647
A15: Colchão Queen Mola Ensacada Probel Cairo Ultra Gel | B15: MLB3482157617 | C15: PA66731 | D15: 4705.9 | E15: 170.6 | F15: 36 | G15: 2999.84 | H15: Elegível | I15: Participar | K15: CANDIDATE-MLB3482157617-77072334467
A16: Colchão Casal Mola Probel Siena | B16: MLB3482170647 | C16: PA66724 | D16: 2980 | E16: 95.46 | F16: 32 | G16: 2025.36 | H16: Elegível | I16: Participar | K16: CANDIDATE-MLB3482170647-77073598995
A17: Colchão King Mola Probel Prohotel Casa | B17: MLB3482209147 | C17: PA66749 | D17: 6686.9 | E17: 197.53 | F17: 30 | G17: 4711.53 | H17: Elegível | I17: Participar | K17: CANDIDATE-MLB3482209147-77071679690
... A253: Colchão Casal Espuma D23 Guarda Costas 138x188x12cm Probel | B253: MLB5904901678 | C253: PA51521 | D253: 1192.9 | E253: 45.82 | F253: 45 | G253: 654.65 | H253: Elegível | I253: Participar | K253: CANDIDATE-MLB5904901678-77073511706

Sheet Boa forma
A1: MLB | B1: SKU | C1: 16.5 | D1: 15.5 | E1: 14.5 | F1: 13.5 | G1: 12.5 | H1: 11.5 | I1: 10.5 | J1: 9.5 | K1: 8.5 | L1: 7.5 | M1: 6.5 | N1: 5.5 | O1: 4.5
A2: MLB6808717242 | B2: PAA8725 | H2: 752.36887 | I2: 730.45522 | J2: 709.17982 | K2: 688.5241 | L2: 668.47 | M2: 649 | N2: 616.55 | O2: 585.7225
A3: MLB6808649520 | B3: PAA8631 | H3: 868.29628 | I3: 843.0061 | J3: 818.45252 | K3: 794.6141 | L3: 771.47 | M3: 749 | N3: 711.55 | O3: 675.9725
A4: MLB4731835429 | B4: PAA8639 | H4: 926.25999 | I4: 899.28154 | J4: 873.08887 | K4: 847.6591 | L4: 822.97 | M4: 799 | N4: 759.05 | O4: 721.0975
A5: MLB6808636794 | B5: PAA8767 | H5: 926.25999 | I5: 899.28154 | J5: 873.08887 | K5: 847.6591 | L5: 822.97 | M5: 799 | N5: 759.05 | O5: 721.0975
A6: MLB6808717436 | B6: PAA8728 | H6: 1100.1511 | I6: 1068.1079 | J6: 1036.9979 | K6: 1006.7941 | L6: 977.47 | M6: 949 | N6: 901.55 | O6: 856.4725
A7: MLB6808717554 | B7: PAA8820 | H7: 1158.1148 | I7: 1124.3833 | J7: 1091.6343 | K7: 1059.8391 | L7: 1028.97 | M7: 999 | N7: 949.05 | O7: 901.5975
A8: MLB4695826589 | B8: PAA8635 | H8: 1274.0422 | I8: 1236.9342 | J8: 1200.907 | K8: 1165.9291 | L8: 1131.97 | M8: 1099 | N8: 1044.05 | O8: 991.8475
A9: MLB4731822293 | B9: PAA8642 | H9: 1355.1914 | I9: 1315.7198 | J9: 1277.3979 | K9: 1240.1921 | L9: 1204.07 | M9: 1169 | N9: 1110.55 | O9: 1055.0225
A10: MLB6808645580 | B10: PAA8770 | H10: 1389.9696 | I10: 1349.4851 | J10: 1310.1797 | K10: 1272.0191 | L10: 1234.97 | M10: 1199 | N10: 1139.05 | O10: 1082.0975
A11: MLB4695831309 | B11: PAA8627 | H11: 1505.897 | I11: 1462.0359 | J11: 1419.4524 | K11: 1378.1091 | L11: 1337.97 | M11: 1299 | N11: 1234.05 | O11: 1172.3475
A12: MLB4731797891 | B12: PAA8643 | H12: 1621.8244 | I12: 1574.5868 | J12: 1528.7251 | K12: 1484.1991 | L12: 1440.97 | M12: 1399 | N12: 1329.05 | O12: 1262.5975
A13: MLB6808658460 | B13: PAA8823 | H13: 1853.6792 | I13: 1799.6886 | J13: 1747.2705 | K13: 1696.3791 | L13: 1646.97 | M13: 1599 | N13: 1519.05 | O13: 1443.0975
... A16: MLB4778272569 | B16: PAB0008 | H16: 2317.3889 | I16: 2249.8921 | J16: 2184.3613 | K16: 2120.7391 | L16: 2058.97 | M16: 1999 | N16: 1899.05 | O16: 1804.0975
A17: MLB4695851191 | B17: PAA8770 | C17: 1646.419 | D17: 1598.4651 | E17: 1551.9078 | F17: 1506.7066 | G17: 1462.822 | H17: 1420.2155 | I17: 1378.85 | J17: 859 | K17: 816.05 | L17: 816.05 | M17: 816.05 | N17: 816.05 | O17: 816.05
A18: MLB6808636794 | B18: PAA8767 | C18: 1097.155 | D18: 1065.199 | E18: 1034.1738 | F18: 1004.0522 | G18: 974.80796 | H18: 946.4155 | I18: 918.85 | J18: 649 | K18: 616.55 | L18: 616.55 | M18: 616.55 | N18: 616.55 | O18: 616.55
A19: MLB4778276509 | B19: PAB0008 | C19: 2744.9471 | D19: 2664.9972 | E19: 2587.3759 | F19: 2512.0155 | G19: 2438.85 | H19: 2367.8155 | I19: 2298.85 | J19: 1965.9251 | K19: 1867.6289 | L19: 1867.6289 | M19: 1867.6289 | N19: 1867.6289 | O19: 1867.6289
A20: MLB4731822453 | B20: PAA8643 | C20: 1921.051 | D20: 1865.0981 | E20: 1810.7748 | F20: 1758.0338 | G20: 1706.829 | H20: 1657.1155 | I20: 1608.85 | J20: 1375.8526 | K20: 1307.0599 | L20: 1307.0599 | M20: 1307.0599 | N20: 1307.0599 | O20: 1307.0599
A21: MLB6888519688 | B21: PAA8639 | C21: 1097.155 | D21: 1065.199 | E21: 1034.1738 | F21: 1004.0522 | G21: 974.80796 | H21: 946.4155 | I21: 918.85 | J21: 785.77999 | K21: 746.49099 | L21: 746.49099 | M21: 746.49099 | N21: 746.49099 | O21: 746.49099
A22: MLB6808636944 | B22: PAA8627 | C22: 1783.735 | D22: 1731.7816 | E22: 1681.3413 | F22: 1632.3702 | G22: 1584.8255 | H22: 1538.6655 | I22: 1493.85 | J22: 1277.5071 | K22: 1213.6318 | L22: 1213.6318 | M22: 1213.6318 | N22: 1213.6318 | O22: 1213.6318
A23: MLB6808611056 | B23: PAA8635 | C23: 1509.103 | D23: 1465.1485 | E23: 1422.4743 | F23: 1381.043 | G23: 1340.8185 | H23: 1301.7655 | I23: 1263.85 | J23: 1080.8163 | K23: 1026.7755 | L23: 1026.7755 | M23: 1026.7755 | N23: 1026.7755 | O23: 1026.7755
A24: MLB6808615938 | B24: PAA8631 | C24: 1028.4969 | D24: 998.54072 | E24: 969.45701 | F24: 941.2204 | G24: 913.80621 | H24: 887.1905 | I24: 861.35 | J24: 736.60727 | K24: 699.77691 | L24: 699.77691 | M24: 699.77691 | N24: 699.77691 | O24: 699.77691
A25: MLB4695880605 | B25: PAA8824 | C25: 2566.4363 | D25: 2491.6857 | E25: 2419.1124 | F25: 2348.6528 | G25: 2280.2454 | H25: 2213.8305 | I25: 2149.35 | J25: 1838.0761 | K25: 1746.1723 | L25: 1746.1723 | M25: 1746.1723 | N25: 1746.1723 | O25: 1746.1723
A26: MLB6888519848 | B26: PAB0007 | C26: 2332.9991 | D26: 2265.0477 | E26: 2199.0754 | F26: 2135.0246 | G26: 2072.8395 | H26: 2012.4655 | I26: 1953.85 | J26: 1670.8889 | K26: 1587.3444 | L26: 1587.3444 | M26: 1587.3444 | N26: 1587.3444 | O26: 1587.3444
A27: MLB4731835191 | B27: PAA8642 | C27: 1605.2242 | D27: 1558.4701 | E27: 1513.0778 | F27: 1469.0075 | G27: 1426.2209 | H27: 1384.6805 | I27: 1344.35 | J27: 1149.6581 | K27: 1092.1752 | L27: 1092.1752 | M27: 1092.1752 | N27: 1092.1752 | O27: 1092.1752
A28: MLB4695851761 | B28: PAA8823 | C28: 2195.6831 | D28: 2131.7311 | E28: 2069.6419 | F28: 2009.361 | G28: 1950.836 | H28: 1894.0155 | I28: 1838.85 | J28: 1572.5434 | K28: 1493.9163 | L28: 1493.9163 | M28: 1493.9163 | N28: 1493.9163 | O28: 1493.9163
... A31: MLB6808645782 | B31: PAA8725 | C31: 891.18093 | D31: 865.22421 | E31: 840.0235 | F31: 815.5568 | G31: 791.80271 | H31: 768.7405 | I31: 746.35 | J31: 638.26184 | K31: 606.34875 | L31: 606.34875 | M31: 606.34875 | N31: 606.34875 | O31: 606.34875

Sheet Base com preços
A1: Cod PA | B1: título | C1: 0.165 | D1: 0.155 | E1: 0.145 | F1: 0.135 | G1: 0.125 | H1: 0.115 | I1: 0.105 | J1: 0.095 | K1: 0.085 | L1: 0.075 | M1: 0.065 | N1: 0.055 | O1: 0.045
C2: Preço c/ comissão 16,5% | D2: Preço c/ comissão 15,5% | E2: Preço c/ comissão 14,5% | F2: Preço c/ comissão 13,5% | G2: Preço c/ comissão 12,5% | H2: Preço c/ comissão 11,5% | I2: Preço c/ comissão 10,5% | J2: Preço c/ comissão 9,5% | K2: Preço c/ comissão 8,5% | L2: Preço c/ comissão 7,5% | M2: Preço c/ comissão 6,5% | N2: Preço c/ comissão 5,5% | O2: Preço c/ comissão 4,5%
A3: PAA4242 | B3: Kit Box Baú Bipartido King com Colchão Mola Probel Prohotel Casa | C3: 10625.122 | D3: 10306.368 | E3: 9997.1769 | F3: 9697.2616 | G3: 9406.3437 | H3: 9124.1534 | I3: 8850.4288 | J3: 8584.916 | K3: 8327.3685 | L3: 8077.5474 | M3: 7835.221 | N3: 7600.1644 | O3: 7372.1594
A4: PAA2452 | B4: Conjunto Box King Mola Ensacada Prodormir Imperium Soft Gel (193x203x78cm) | C4: 9324.6652 | D4: 9044.9252 | E4: 8773.5774 | F4: 8510.3701 | G4: 8255.059 | H4: 8007.4072 | I4: 7767.185 | J4: 7534.1695 | K4: 7308.1444 | L4: 7088.9001 | M4: 6876.2331 | N4: 6669.9461 | O4: 6469.8477
A5: PAA4246 | B5: Kit Box Baú Bipartido King com Colchão Mola Ensacada Probel Munique | C5: 8990.0448 | D5: 8720.3435 | E5: 8458.7332 | F5: 8204.9712 | G5: 7958.822 | H5: 7720.0574 | I5: 7488.4557 | J5: 7263.802 | K5: 7045.8879 | L5: 6834.5113 | M5: 6629.476 | N5: 6430.5917 | O5: 6237.6739
A6: PAA4224 | B6: Kit Box Baú Bipartido King com Colchão Mola Ensacada Probel Versailles Ultra Gel | C6: 8522.4917 | D6: 8266.817 | E6: 8018.8125 | F6: 7778.2481 | G6: 7544.9006 | H6: 7318.5536 | I6: 7098.997 | J6: 6886.0271 | K6: 6679.4463 | L6: 6479.0629 | M6: 6284.691 | N6: 6096.1503 | O6: 5913.2658
A7: PAA4237 | B7: Kit Box Baú Bipartido King com Colchão Mola Ensacada Probel Cairo Ultra Gel | C7: 8407.8615 | D7: 8155.6256 | E7: 7910.9568 | F7: 7673.6281 | G7: 7443.4193 | H7: 7220.1167 | I7: 7003.5132 | J7: 6793.4078 | K7: 6589.6056 | L7: 6391.9174 | M7: 6200.1599 | N7: 6014.1551 | O7: 5833.7304
A8: PAA4219 | B8: Kit Box Baú Bipartido King com Colchão Mola Probel Volare Luxo | C8: 8289.2227 | D8: 8040.546 | E8: 7799.3296 | F8: 7565.3497 | G8: 7338.3892 | H8: 7118.2376 | I8: 6904.6904 | J8: 6697.5497 | K8: 6496.6232 | L8: 6301.7245 | M8: 6112.6728 | N8: 5929.2926 | O8: 5751.4138
A9: PAA2438 | B9: Conjunto Box King Mola Ensacada Prodormir New Paris (193x203x74cm) | C9: 8287.268 | D9: 8038.65 | E9: 7797.4905 | F9: 7563.5657 | G9: 7336.6588 | H9: 7116.559 | I9: 6903.0622 | J9: 6695.9704 | K9: 6495.0913 | L9: 6300.2385 | M9: 6111.2314 | N9: 5927.8944 | O9: 5750.0576
A10: PAA4228 | B10: Kit Box Baú Bipartido King com Colchão Mola Ensacada Probel Bari | C10: 8044.2119 | D10: 7802.8856 | E10: 7568.799 | F10: 7341.735 | G10: 7121.483 | H10: 6907.8385 | I10: 6700.6033 | J10: 6499.5852 | K10: 6304.5977 | L10: 6115.4597 | M10: 5931.9959 | N10: 5754.0361 | O10: 5581.415
A11: PAA4241 | B11: Kit Box Baú Bipartido Queen com Colchão Mola Probel Prohotel Casa | C11: 8020.6596 | D11: 7780.0398 | E11: 7546.6387 | F11: 7320.2395 | G11: 7100.6323 | H11: 6887.6133 | I11: 6680.9849 | J11: 6480.5554 | K11: 6286.1387 | L11: 6097.5546 | M11: 5914.6279 | N11: 5737.1891 | O11: 5565.0734
A12: PAA4251 | B12: Kit Box Baú Bipartido King com Colchão Mola Ensacada Probel Excede Premium | C12: 7964.8155 | D12: 7725.871 | E12: 7494.0949 | F12: 7269.272 | G12: 7051.1939 | H12: 6839.658 | I12: 6634.4683 | J12: 6435.4342 | K12: 6242.3712 | L12: 6055.1001 | M12: 5873.4471 | N12: 5697.2437 | O12: 5526.3264
A13: PAA4233 | B13: Kit Box Baú Bipartido King com Colchão Mola Probel Siena | C13: 7518.2942 | D13: 7292.7454 | E13: 7073.963 | F13: 6861.7442 | G13: 6655.8918 | H13: 6456.2151 | I13: 6262.5286 | J13: 6074.6528 | K13: 5892.4132 | L13: 5715.6408 | M13: 5544.1716 | N13: 5377.8464 | O13: 5216.511
A14: PAA4256 | B14: Kit Box Baú Bipartido King com Colchão Mola Ensacada Probel Turim Springs | C14: 7440.5063 | D14: 7217.2912 | E14: 7000.7724 | F14: 6790.7493 | G14: 6587.0268 | H14: 6389.416 | I14: 6197.7335 | J14: 6011.8015 | K14: 5831.4474 | L14: 5656.504 | M14: 5486.8089 | N14: 5322.2046 | O14: 5162.5385
... A1869: PAA2685 | B1869: Travesseiro Probel Elos Flocos de Espuma Macio 12cm (alt) | C1869: 49.874396 | D1869: 48.378164 | E1869: 46.926819 | F1869: 45.519015 | G1869: 44.153444 | H1869: 42.828841 | I1869: 41.543976 | J1869: 40.297656 | K1869: 39.088727 | L1869: 37.916065 | M1869: 36.778583 | N1869: 35.675225 | O1869: 34.604969
A1870: PA84467
A1871: PA62152
A1872: PA65752
